{"code":"0000","message":"\u6210\u529f","data":{"1":[{"id":"79476","school_id":"2462","special_id":"306","nation_feature":"2","province_feature":"2","is_important":"2","limit_year":"\u56db\u5e74","year":"2022","level3_weight":"0","nation_first_class":"2","xueke_rank":"0","xueke_rank_score":"","ruanke_rank":"9999","ruanke_level":"","is_video":2,"special_name":"\u6587\u5316\u4ea7\u4e1a\u7ba1\u7406","special_type":"1","type_name":"\u672c\u79d1","level3_name":"\u5de5\u5546\u7ba1\u7406\u7c7b","level3_code":"113","level2_name":"\u7ba1\u7406\u5b66","level2_id":"13","level2_code":"12","code":"1202"},{"id":"79475","school_id":"2462","special_id":"165","nation_feature":"2","province_feature":"2","is_important":"2","limit_year":"\u56db\u5e74","year":"2022","level3_weight":"0","nation_first_class":"2","xueke_rank":"0","xueke_rank_score":"","ruanke_rank":"9999","ruanke_level":"","is_video":2,"special_name":"\u7535\u5b50\u4fe1\u606f\u5de5\u7a0b","special_type":"1","type_name":"\u672c\u79d1","level3_name":"\u7535\u5b50\u4fe1\u606f\u7c7b","level3_code":"69","level2_name":"\u5de5\u5b66","level2_id":"10","level2_code":"08","code":"0807"},{"id":"79473","school_id":"2462","special_id":"110","nation_feature":"2","province_feature":"2","is_important":"2","limit_year":"\u56db\u5e74","year":"2022","level3_weight":"0","nation_first_class":"2","xueke_rank":"0","xueke_rank_score":"","ruanke_rank":"9999","ruanke_level":"","is_video":2,"special_name":"\u4f20\u64ad\u5b66","special_type":"1","type_name":"\u672c\u79d1","level3_name":"\u65b0\u95fb\u4f20\u64ad\u5b66\u7c7b","level3_code":"49","level2_name":"\u6587\u5b66","level2_id":"7","level2_code":"05","code":"0503"},{"id":"79472","school_id":"2462","special_id":"108","nation_feature":"2","province_feature":"2","is_important":"2","limit_year":"\u56db\u5e74","year":"2022","level3_weight":"0","nation_first_class":"2","xueke_rank":"0","xueke_rank_score":"","ruanke_rank":"9999","ruanke_level":"","is_video":2,"special_name":"\u5e7f\u64ad\u7535\u89c6\u5b66","special_type":"1","type_name":"\u672c\u79d1","level3_name":"\u65b0\u95fb\u4f20\u64ad\u5b66\u7c7b","level3_code":"49","level2_name":"\u6587\u5b66","level2_id":"7","level2_code":"05","code":"0503"},{"id":"79471","school_id":"2462","special_id":"45","nation_feature":"2","province_feature":"2","is_important":"2","limit_year":"\u56db\u5e74","year":"2022","level3_weight":"0","nation_first_class":"2","xueke_rank":"0","xueke_rank_score":"","ruanke_rank":"9999","ruanke_level":"","is_video":2,"special_name":"\u82f1\u8bed","special_type":"1","type_name":"\u672c\u79d1","level3_name":"\u5916\u56fd\u8bed\u8a00\u6587\u5b66\u7c7b","level3_code":"48","level2_name":"\u6587\u5b66","level2_id":"7","level2_code":"05","code":"0502"},{"id":"79470","school_id":"2462","special_id":"40","nation_feature":"2","province_feature":"2","is_important":"2","limit_year":"\u56db\u5e74","year":"2022","level3_weight":"0","nation_first_class":"2","xueke_rank":"0","xueke_rank_score":"","ruanke_rank":"9999","ruanke_level":"","is_video":2,"special_name":"\u6c49\u8bed\u8a00\u6587\u5b66","special_type":"1","type_name":"\u672c\u79d1","level3_name":"\u4e2d\u56fd\u8bed\u8a00\u6587\u5b66\u7c7b","level3_code":"47","level2_name":"\u6587\u5b66","level2_id":"7","level2_code":"05","code":"0501"},{"id":"79468","school_id":"2462","special_id":"320","nation_feature":"2","province_feature":"2","is_important":"2","limit_year":"\u56db\u5e74","year":"2022","level3_weight":"0","nation_first_class":"2","xueke_rank":"0","xueke_rank_score":"","ruanke_rank":"9999","ruanke_level":"","is_video":2,"special_name":"\u7535\u5b50\u5546\u52a1","special_type":"1","type_name":"\u672c\u79d1","level3_name":"\u7535\u5b50\u5546\u52a1\u7c7b","level3_code":"119","level2_name":"\u7ba1\u7406\u5b66","level2_id":"13","level2_code":"12","code":"1208"},{"id":"79465","school_id":"2462","special_id":"1157","nation_feature":"2","province_feature":"2","is_important":"2","limit_year":"\u56db\u5e74","year":"2022","level3_weight":"0","nation_first_class":"2","xueke_rank":"0","xueke_rank_score":"","ruanke_rank":"9999","ruanke_level":"","is_video":2,"special_name":"\u5e7f\u64ad\u7535\u89c6\u5de5\u7a0b","special_type":"1","type_name":"\u672c\u79d1","level3_name":"\u7535\u5b50\u4fe1\u606f\u7c7b","level3_code":"69","level2_name":"\u5de5\u5b66","level2_id":"10","level2_code":"08","code":"0807"},{"id":"704573","school_id":"2462","special_id":"346","nation_feature":"2","province_feature":"2","is_important":"2","limit_year":"\u56db\u5e74","year":"2022","level3_weight":"0","nation_first_class":"2","xueke_rank":"0","xueke_rank_score":"","ruanke_rank":"9999","ruanke_level":"","is_video":2,"special_name":"\u89c6\u89c9\u4f20\u8fbe\u8bbe\u8ba1","special_type":"1","type_name":"\u672c\u79d1","level3_name":"\u8bbe\u8ba1\u5b66\u7c7b","level3_code":"125","level2_name":"\u827a\u672f\u5b66","level2_id":"14","level2_code":"13","code":"1305"},{"id":"704575","school_id":"2462","special_id":"335","nation_feature":"2","province_feature":"2","is_important":"2","limit_year":"\u56db\u5e74","year":"2022","level3_weight":"0","nation_first_class":"2","xueke_rank":"0","xueke_rank_score":"","ruanke_rank":"9999","ruanke_level":"","is_video":2,"special_name":"\u5e7f\u64ad\u7535\u89c6\u7f16\u5bfc","special_type":"1","type_name":"\u672c\u79d1","level3_name":"\u620f\u5267\u4e0e\u5f71\u89c6\u5b66\u7c7b","level3_code":"123","level2_name":"\u827a\u672f\u5b66","level2_id":"14","level2_code":"13","code":"1303"},{"id":"761937","school_id":"2462","special_id":"325","nation_feature":"2","province_feature":"2","is_important":"2","limit_year":"\u56db\u5e74","year":"2022","level3_weight":"0","nation_first_class":"2","xueke_rank":"0","xueke_rank_score":"","ruanke_rank":"9999","ruanke_level":"","is_video":2,"special_name":"\u97f3\u4e50\u8868\u6f14","special_type":"1","type_name":"\u672c\u79d1","level3_name":"\u97f3\u4e50\u4e0e\u821e\u8e48\u5b66\u7c7b","level3_code":"122","level2_name":"\u827a\u672f\u5b66","level2_id":"14","level2_code":"13","code":"1302"},{"id":"761938","school_id":"2462","special_id":"326","nation_feature":"2","province_feature":"2","is_important":"2","limit_year":"\u4e94\u5e74","year":"2022","level3_weight":"0","nation_first_class":"2","xueke_rank":"0","xueke_rank_score":"","ruanke_rank":"9999","ruanke_level":"","is_video":2,"special_name":"\u97f3\u4e50\u5b66","special_type":"1","type_name":"\u672c\u79d1","level3_name":"\u97f3\u4e50\u4e0e\u821e\u8e48\u5b66\u7c7b","level3_code":"122","level2_name":"\u827a\u672f\u5b66","level2_id":"14","level2_code":"13","code":"1302"},{"id":"1023066","school_id":"2462","special_id":"340","nation_feature":"2","province_feature":"2","is_important":"2","limit_year":"\u56db\u5e74","year":"2022","level3_weight":"0","nation_first_class":"2","xueke_rank":"0","xueke_rank_score":"","ruanke_rank":"9999","ruanke_level":"","is_video":2,"special_name":"\u52a8\u753b","special_type":"1","type_name":"\u672c\u79d1","level3_name":"\u620f\u5267\u4e0e\u5f71\u89c6\u5b66\u7c7b","level3_code":"123","level2_name":"\u827a\u672f\u5b66","level2_id":"14","level2_code":"13","code":"1303"},{"id":"1023067","school_id":"2462","special_id":"352","nation_feature":"2","province_feature":"2","is_important":"2","limit_year":"\u56db\u5e74","year":"2022","level3_weight":"0","nation_first_class":"2","xueke_rank":"0","xueke_rank_score":"","ruanke_rank":"9999","ruanke_level":"","is_video":2,"special_name":"\u6570\u5b57\u5a92\u4f53\u827a\u672f","special_type":"1","type_name":"\u672c\u79d1","level3_name":"\u8bbe\u8ba1\u5b66\u7c7b","level3_code":"125","level2_name":"\u827a\u672f\u5b66","level2_id":"14","level2_code":"13","code":"1305"},{"id":"1023068","school_id":"2462","special_id":"337","nation_feature":"2","province_feature":"2","is_important":"2","limit_year":"\u56db\u5e74","year":"2022","level3_weight":"0","nation_first_class":"2","xueke_rank":"0","xueke_rank_score":"","ruanke_rank":"9999","ruanke_level":"","is_video":2,"special_name":"\u620f\u5267\u5f71\u89c6\u7f8e\u672f\u8bbe\u8ba1","special_type":"1","type_name":"\u672c\u79d1","level3_name":"\u620f\u5267\u4e0e\u5f71\u89c6\u5b66\u7c7b","level3_code":"123","level2_name":"\u827a\u672f\u5b66","level2_id":"14","level2_code":"13","code":"1303"}],"2":[{"id":"159132","school_id":"2462","special_id":"974","nation_feature":"2","province_feature":"2","is_important":"2","limit_year":"\u4e09\u5e74","year":"2022","level3_weight":"0","nation_first_class":"2","xueke_rank":"0","xueke_rank_score":"","ruanke_rank":"9999","ruanke_level":"","is_video":2,"special_name":"\u65b0\u95fb\u91c7\u7f16\u4e0e\u5236\u4f5c","special_type":"2","type_name":"\u4e13\u79d1\uff08\u9ad8\u804c\uff09","level3_name":"\u5e7f\u64ad\u5f71\u89c6\u7c7b","level3_code":"210","level2_name":"\u65b0\u95fb\u4f20\u64ad\u5927\u7c7b","level2_id":"30","level2_code":"56","code":"5602"},{"id":"159133","school_id":"2462","special_id":"886","nation_feature":"2","province_feature":"2","is_important":"2","limit_year":"\u4e09\u5e74","year":"2022","level3_weight":"0","nation_first_class":"2","xueke_rank":"0","xueke_rank_score":"","ruanke_rank":"9999","ruanke_level":"","is_video":2,"special_name":"\u7535\u5b50\u5546\u52a1","special_type":"2","type_name":"\u4e13\u79d1\uff08\u9ad8\u804c\uff09","level3_name":"\u7535\u5b50\u5546\u52a1\u7c7b","level3_code":"200","level2_name":"\u8d22\u7ecf\u5546\u8d38\u5927\u7c7b","level2_id":"27","level2_code":"53","code":"5307"},{"id":"1791417","school_id":"2462","special_id":"979","nation_feature":"2","province_feature":"2","is_important":"2","limit_year":"\u4e09\u5e74","year":"2022","level3_weight":"0","nation_first_class":"2","xueke_rank":"0","xueke_rank_score":"","ruanke_rank":"9999","ruanke_level":"","is_video":2,"special_name":"\u5f71\u89c6\u7f16\u5bfc","special_type":"2","type_name":"\u4e13\u79d1\uff08\u9ad8\u804c\uff09","level3_name":"\u5e7f\u64ad\u5f71\u89c6\u7c7b","level3_code":"210","level2_name":"\u65b0\u95fb\u4f20\u64ad\u5927\u7c7b","level2_id":"30","level2_code":"56","code":"5602"},{"id":"1791418","school_id":"2462","special_id":"975","nation_feature":"2","province_feature":"2","is_important":"2","limit_year":"\u4e09\u5e74","year":"2022","level3_weight":"0","nation_first_class":"2","xueke_rank":"0","xueke_rank_score":"","ruanke_rank":"9999","ruanke_level":"","is_video":2,"special_name":"\u64ad\u97f3\u4e0e\u4e3b\u6301","special_type":"2","type_name":"\u4e13\u79d1\uff08\u9ad8\u804c\uff09","level3_name":"\u5e7f\u64ad\u5f71\u89c6\u7c7b","level3_code":"210","level2_name":"\u65b0\u95fb\u4f20\u64ad\u5927\u7c7b","level2_id":"30","level2_code":"56","code":"5602"},{"id":"1791419","school_id":"2462","special_id":"934","nation_feature":"2","province_feature":"2","is_important":"2","limit_year":"\u4e09\u5e74","year":"2022","level3_weight":"0","nation_first_class":"2","xueke_rank":"0","xueke_rank_score":"","ruanke_rank":"9999","ruanke_level":"","is_video":2,"special_name":"\u620f\u5267\u5f71\u89c6\u8868\u6f14","special_type":"2","type_name":"\u4e13\u79d1\uff08\u9ad8\u804c\uff09","level3_name":"\u8868\u6f14\u827a\u672f\u7c7b","level3_code":"206","level2_name":"\u6587\u5316\u827a\u672f\u5927\u7c7b","level2_id":"29","level2_code":"55","code":"5502"},{"id":"1791420","school_id":"2462","special_id":"982","nation_feature":"2","province_feature":"2","is_important":"2","limit_year":"\u4e09\u5e74","year":"2022","level3_weight":"0","nation_first_class":"2","xueke_rank":"0","xueke_rank_score":"","ruanke_rank":"9999","ruanke_level":"","is_video":2,"special_name":"\u5f71\u89c6\u52a8\u753b","special_type":"2","type_name":"\u4e13\u79d1\uff08\u9ad8\u804c\uff09","level3_name":"\u5e7f\u64ad\u5f71\u89c6\u7c7b","level3_code":"210","level2_name":"\u65b0\u95fb\u4f20\u64ad\u5927\u7c7b","level2_id":"30","level2_code":"56","code":"5602"}],"special_detail":{"1":[{"id":"79476","school_id":"2462","special_id":"306","nation_feature":"2","province_feature":"2","is_important":"2","limit_year":"\u56db\u5e74","year":"2022","level3_weight":"0","nation_first_class":"2","xueke_rank":"0","xueke_rank_score":"","ruanke_rank":"9999","ruanke_level":"","is_video":2,"special_name":"\u6587\u5316\u4ea7\u4e1a\u7ba1\u7406","special_type":"1","type_name":"\u672c\u79d1","level3_name":"\u5de5\u5546\u7ba1\u7406\u7c7b","level3_code":"113","level2_name":"\u7ba1\u7406\u5b66","level2_id":"13","level2_code":"12","code":"1202"},{"id":"79475","school_id":"2462","special_id":"165","nation_feature":"2","province_feature":"2","is_important":"2","limit_year":"\u56db\u5e74","year":"2022","level3_weight":"0","nation_first_class":"2","xueke_rank":"0","xueke_rank_score":"","ruanke_rank":"9999","ruanke_level":"","is_video":2,"special_name":"\u7535\u5b50\u4fe1\u606f\u5de5\u7a0b","special_type":"1","type_name":"\u672c\u79d1","level3_name":"\u7535\u5b50\u4fe1\u606f\u7c7b","level3_code":"69","level2_name":"\u5de5\u5b66","level2_id":"10","level2_code":"08","code":"0807"},{"id":"79473","school_id":"2462","special_id":"110","nation_feature":"2","province_feature":"2","is_important":"2","limit_year":"\u56db\u5e74","year":"2022","level3_weight":"0","nation_first_class":"2","xueke_rank":"0","xueke_rank_score":"","ruanke_rank":"9999","ruanke_level":"","is_video":2,"special_name":"\u4f20\u64ad\u5b66","special_type":"1","type_name":"\u672c\u79d1","level3_name":"\u65b0\u95fb\u4f20\u64ad\u5b66\u7c7b","level3_code":"49","level2_name":"\u6587\u5b66","level2_id":"7","level2_code":"05","code":"0503"},{"id":"79472","school_id":"2462","special_id":"108","nation_feature":"2","province_feature":"2","is_important":"2","limit_year":"\u56db\u5e74","year":"2022","level3_weight":"0","nation_first_class":"2","xueke_rank":"0","xueke_rank_score":"","ruanke_rank":"9999","ruanke_level":"","is_video":2,"special_name":"\u5e7f\u64ad\u7535\u89c6\u5b66","special_type":"1","type_name":"\u672c\u79d1","level3_name":"\u65b0\u95fb\u4f20\u64ad\u5b66\u7c7b","level3_code":"49","level2_name":"\u6587\u5b66","level2_id":"7","level2_code":"05","code":"0503"},{"id":"79471","school_id":"2462","special_id":"45","nation_feature":"2","province_feature":"2","is_important":"2","limit_year":"\u56db\u5e74","year":"2022","level3_weight":"0","nation_first_class":"2","xueke_rank":"0","xueke_rank_score":"","ruanke_rank":"9999","ruanke_level":"","is_video":2,"special_name":"\u82f1\u8bed","special_type":"1","type_name":"\u672c\u79d1","level3_name":"\u5916\u56fd\u8bed\u8a00\u6587\u5b66\u7c7b","level3_code":"48","level2_name":"\u6587\u5b66","level2_id":"7","level2_code":"05","code":"0502"},{"id":"79470","school_id":"2462","special_id":"40","nation_feature":"2","province_feature":"2","is_important":"2","limit_year":"\u56db\u5e74","year":"2022","level3_weight":"0","nation_first_class":"2","xueke_rank":"0","xueke_rank_score":"","ruanke_rank":"9999","ruanke_level":"","is_video":2,"special_name":"\u6c49\u8bed\u8a00\u6587\u5b66","special_type":"1","type_name":"\u672c\u79d1","level3_name":"\u4e2d\u56fd\u8bed\u8a00\u6587\u5b66\u7c7b","level3_code":"47","level2_name":"\u6587\u5b66","level2_id":"7","level2_code":"05","code":"0501"},{"id":"79468","school_id":"2462","special_id":"320","nation_feature":"2","province_feature":"2","is_important":"2","limit_year":"\u56db\u5e74","year":"2022","level3_weight":"0","nation_first_class":"2","xueke_rank":"0","xueke_rank_score":"","ruanke_rank":"9999","ruanke_level":"","is_video":2,"special_name":"\u7535\u5b50\u5546\u52a1","special_type":"1","type_name":"\u672c\u79d1","level3_name":"\u7535\u5b50\u5546\u52a1\u7c7b","level3_code":"119","level2_name":"\u7ba1\u7406\u5b66","level2_id":"13","level2_code":"12","code":"1208"},{"id":"79465","school_id":"2462","special_id":"1157","nation_feature":"2","province_feature":"2","is_important":"2","limit_year":"\u56db\u5e74","year":"2022","level3_weight":"0","nation_first_class":"2","xueke_rank":"0","xueke_rank_score":"","ruanke_rank":"9999","ruanke_level":"","is_video":2,"special_name":"\u5e7f\u64ad\u7535\u89c6\u5de5\u7a0b","special_type":"1","type_name":"\u672c\u79d1","level3_name":"\u7535\u5b50\u4fe1\u606f\u7c7b","level3_code":"69","level2_name":"\u5de5\u5b66","level2_id":"10","level2_code":"08","code":"0807"},{"id":"704573","school_id":"2462","special_id":"346","nation_feature":"2","province_feature":"2","is_important":"2","limit_year":"\u56db\u5e74","year":"2022","level3_weight":"0","nation_first_class":"2","xueke_rank":"0","xueke_rank_score":"","ruanke_rank":"9999","ruanke_level":"","is_video":2,"special_name":"\u89c6\u89c9\u4f20\u8fbe\u8bbe\u8ba1","special_type":"1","type_name":"\u672c\u79d1","level3_name":"\u8bbe\u8ba1\u5b66\u7c7b","level3_code":"125","level2_name":"\u827a\u672f\u5b66","level2_id":"14","level2_code":"13","code":"1305"},{"id":"704575","school_id":"2462","special_id":"335","nation_feature":"2","province_feature":"2","is_important":"2","limit_year":"\u56db\u5e74","year":"2022","level3_weight":"0","nation_first_class":"2","xueke_rank":"0","xueke_rank_score":"","ruanke_rank":"9999","ruanke_level":"","is_video":2,"special_name":"\u5e7f\u64ad\u7535\u89c6\u7f16\u5bfc","special_type":"1","type_name":"\u672c\u79d1","level3_name":"\u620f\u5267\u4e0e\u5f71\u89c6\u5b66\u7c7b","level3_code":"123","level2_name":"\u827a\u672f\u5b66","level2_id":"14","level2_code":"13","code":"1303"},{"id":"761937","school_id":"2462","special_id":"325","nation_feature":"2","province_feature":"2","is_important":"2","limit_year":"\u56db\u5e74","year":"2022","level3_weight":"0","nation_first_class":"2","xueke_rank":"0","xueke_rank_score":"","ruanke_rank":"9999","ruanke_level":"","is_video":2,"special_name":"\u97f3\u4e50\u8868\u6f14","special_type":"1","type_name":"\u672c\u79d1","level3_name":"\u97f3\u4e50\u4e0e\u821e\u8e48\u5b66\u7c7b","level3_code":"122","level2_name":"\u827a\u672f\u5b66","level2_id":"14","level2_code":"13","code":"1302"},{"id":"761938","school_id":"2462","special_id":"326","nation_feature":"2","province_feature":"2","is_important":"2","limit_year":"\u4e94\u5e74","year":"2022","level3_weight":"0","nation_first_class":"2","xueke_rank":"0","xueke_rank_score":"","ruanke_rank":"9999","ruanke_level":"","is_video":2,"special_name":"\u97f3\u4e50\u5b66","special_type":"1","type_name":"\u672c\u79d1","level3_name":"\u97f3\u4e50\u4e0e\u821e\u8e48\u5b66\u7c7b","level3_code":"122","level2_name":"\u827a\u672f\u5b66","level2_id":"14","level2_code":"13","code":"1302"},{"id":"1023066","school_id":"2462","special_id":"340","nation_feature":"2","province_feature":"2","is_important":"2","limit_year":"\u56db\u5e74","year":"2022","level3_weight":"0","nation_first_class":"2","xueke_rank":"0","xueke_rank_score":"","ruanke_rank":"9999","ruanke_level":"","is_video":2,"special_name":"\u52a8\u753b","special_type":"1","type_name":"\u672c\u79d1","level3_name":"\u620f\u5267\u4e0e\u5f71\u89c6\u5b66\u7c7b","level3_code":"123","level2_name":"\u827a\u672f\u5b66","level2_id":"14","level2_code":"13","code":"1303"},{"id":"1023067","school_id":"2462","special_id":"352","nation_feature":"2","province_feature":"2","is_important":"2","limit_year":"\u56db\u5e74","year":"2022","level3_weight":"0","nation_first_class":"2","xueke_rank":"0","xueke_rank_score":"","ruanke_rank":"9999","ruanke_level":"","is_video":2,"special_name":"\u6570\u5b57\u5a92\u4f53\u827a\u672f","special_type":"1","type_name":"\u672c\u79d1","level3_name":"\u8bbe\u8ba1\u5b66\u7c7b","level3_code":"125","level2_name":"\u827a\u672f\u5b66","level2_id":"14","level2_code":"13","code":"1305"},{"id":"1023068","school_id":"2462","special_id":"337","nation_feature":"2","province_feature":"2","is_important":"2","limit_year":"\u56db\u5e74","year":"2022","level3_weight":"0","nation_first_class":"2","xueke_rank":"0","xueke_rank_score":"","ruanke_rank":"9999","ruanke_level":"","is_video":2,"special_name":"\u620f\u5267\u5f71\u89c6\u7f8e\u672f\u8bbe\u8ba1","special_type":"1","type_name":"\u672c\u79d1","level3_name":"\u620f\u5267\u4e0e\u5f71\u89c6\u5b66\u7c7b","level3_code":"123","level2_name":"\u827a\u672f\u5b66","level2_id":"14","level2_code":"13","code":"1303"},{"id":"2012553","school_id":"2462","special_id":"8442","nation_feature":"2","province_feature":"2","is_important":"2","limit_year":"\u56db\u5e74","year":"2022","level3_weight":"0","nation_first_class":"2","xueke_rank":"0","xueke_rank_score":"","ruanke_rank":"9999","ruanke_level":"","is_video":2,"special_name":"\u620f\u5267\u6559\u80b2","special_type":"1","type_name":"\u672c\u79d1","level3_name":"\u620f\u5267\u4e0e\u5f71\u89c6\u5b66\u7c7b","level3_code":"123","level2_name":"\u827a\u672f\u5b66","level2_id":"14","level2_code":"13","code":"1303"},{"id":"159129","school_id":"2462","special_id":"1130","nation_feature":"2","province_feature":"2","is_important":"2","limit_year":"\u56db\u5e74","year":"2022","level3_weight":"0","nation_first_class":"2","xueke_rank":"0","xueke_rank_score":"","ruanke_rank":"9999","ruanke_level":"","is_video":2,"special_name":"\u7f51\u7edc\u4e0e\u65b0\u5a92\u4f53","special_type":"1","type_name":"\u672c\u79d1","level3_name":"\u65b0\u95fb\u4f20\u64ad\u5b66\u7c7b","level3_code":"49","level2_name":"\u6587\u5b66","level2_id":"7","level2_code":"05","code":"0503"},{"id":"159130","school_id":"2462","special_id":"109","nation_feature":"2","province_feature":"2","is_important":"2","limit_year":"\u56db\u5e74","year":"2022","level3_weight":"0","nation_first_class":"2","xueke_rank":"0","xueke_rank_score":"","ruanke_rank":"9999","ruanke_level":"","is_video":2,"special_name":"\u5e7f\u544a\u5b66","special_type":"1","type_name":"\u672c\u79d1","level3_name":"\u65b0\u95fb\u4f20\u64ad\u5b66\u7c7b","level3_code":"49","level2_name":"\u6587\u5b66","level2_id":"7","level2_code":"05","code":"0503"},{"id":"159131","school_id":"2462","special_id":"323","nation_feature":"2","province_feature":"2","is_important":"2","limit_year":"\u56db\u5e74","year":"2022","level3_weight":"0","nation_first_class":"2","xueke_rank":"0","xueke_rank_score":"","ruanke_rank":"9999","ruanke_level":"","is_video":2,"special_name":"\u4f1a\u5c55\u7ecf\u6d4e\u4e0e\u7ba1\u7406","special_type":"1","type_name":"\u672c\u79d1","level3_name":"\u65c5\u6e38\u7ba1\u7406\u7c7b","level3_code":"120","level2_name":"\u7ba1\u7406\u5b66","level2_id":"13","level2_code":"12","code":"1209"},{"id":"159134","school_id":"2462","special_id":"173","nation_feature":"2","province_feature":"2","is_important":"2","limit_year":"\u56db\u5e74","year":"2022","level3_weight":"0","nation_first_class":"2","xueke_rank":"0","xueke_rank_score":"","ruanke_rank":"9999","ruanke_level":"","is_video":2,"special_name":"\u8f6f\u4ef6\u5de5\u7a0b","special_type":"1","type_name":"\u672c\u79d1","level3_name":"\u8ba1\u7b97\u673a\u7c7b","level3_code":"71","level2_name":"\u5de5\u5b66","level2_id":"10","level2_code":"08","code":"0809"},{"id":"1035938","school_id":"2462","special_id":"331","nation_feature":"2","province_feature":"2","is_important":"2","limit_year":"\u56db\u5e74","year":"2022","level3_weight":"0","nation_first_class":"2","xueke_rank":"0","xueke_rank_score":"","ruanke_rank":"9999","ruanke_level":"","is_video":2,"special_name":"\u8868\u6f14\uff08\u6f14\u827a\u4e3b\u6301)","special_type":"1","type_name":"\u672c\u79d1","level3_name":"\u620f\u5267\u4e0e\u5f71\u89c6\u5b66\u7c7b","level3_code":"123","level2_name":"\u827a\u672f\u5b66","level2_id":"14","level2_code":"13","code":"1303"},{"id":"171983","school_id":"2462","special_id":"334","nation_feature":"2","province_feature":"2","is_important":"2","limit_year":"\u56db\u5e74","year":"2022","level3_weight":"0","nation_first_class":"2","xueke_rank":"0","xueke_rank_score":"","ruanke_rank":"9999","ruanke_level":"","is_video":2,"special_name":"\u620f\u5267\u5f71\u89c6\u6587\u5b66","special_type":"1","type_name":"\u672c\u79d1","level3_name":"\u620f\u5267\u4e0e\u5f71\u89c6\u5b66\u7c7b","level3_code":"123","level2_name":"\u827a\u672f\u5b66","level2_id":"14","level2_code":"13","code":"1303"},{"id":"171984","school_id":"2462","special_id":"331","nation_feature":"2","province_feature":"2","is_important":"2","limit_year":"\u56db\u5e74","year":"2022","level3_weight":"0","nation_first_class":"2","xueke_rank":"0","xueke_rank_score":"","ruanke_rank":"9999","ruanke_level":"","is_video":2,"special_name":"\u8868\u6f14","special_type":"1","type_name":"\u672c\u79d1","level3_name":"\u620f\u5267\u4e0e\u5f71\u89c6\u5b66\u7c7b","level3_code":"123","level2_name":"\u827a\u672f\u5b66","level2_id":"14","level2_code":"13","code":"1303"},{"id":"171985","school_id":"2462","special_id":"329","nation_feature":"2","province_feature":"2","is_important":"2","limit_year":"\u56db\u5e74","year":"2022","level3_weight":"0","nation_first_class":"2","xueke_rank":"0","xueke_rank_score":"","ruanke_rank":"9999","ruanke_level":"","is_video":2,"special_name":"\u821e\u8e48\u5b66","special_type":"1","type_name":"\u672c\u79d1","level3_name":"\u97f3\u4e50\u4e0e\u821e\u8e48\u5b66\u7c7b","level3_code":"122","level2_name":"\u827a\u672f\u5b66","level2_id":"14","level2_code":"13","code":"1302"},{"id":"171986","school_id":"2462","special_id":"344","nation_feature":"2","province_feature":"2","is_important":"2","limit_year":"\u56db\u5e74","year":"2022","level3_weight":"0","nation_first_class":"2","xueke_rank":"0","xueke_rank_score":"","ruanke_rank":"9999","ruanke_level":"","is_video":2,"special_name":"\u6444\u5f71","special_type":"1","type_name":"\u672c\u79d1","level3_name":"\u7f8e\u672f\u5b66\u7c7b","level3_code":"124","level2_name":"\u827a\u672f\u5b66","level2_id":"14","level2_code":"13","code":"1304"},{"id":"171987","school_id":"2462","special_id":"336","nation_feature":"2","province_feature":"2","is_important":"2","limit_year":"\u56db\u5e74","year":"2022","level3_weight":"0","nation_first_class":"2","xueke_rank":"0","xueke_rank_score":"","ruanke_rank":"9999","ruanke_level":"","is_video":2,"special_name":"\u620f\u5267\u5f71\u89c6\u5bfc\u6f14","special_type":"1","type_name":"\u672c\u79d1","level3_name":"\u620f\u5267\u4e0e\u5f71\u89c6\u5b66\u7c7b","level3_code":"123","level2_name":"\u827a\u672f\u5b66","level2_id":"14","level2_code":"13","code":"1303"},{"id":"171988","school_id":"2462","special_id":"1248","nation_feature":"2","province_feature":"2","is_important":"2","limit_year":"\u56db\u5e74","year":"2022","level3_weight":"0","nation_first_class":"2","xueke_rank":"0","xueke_rank_score":"","ruanke_rank":"9999","ruanke_level":"","is_video":2,"special_name":"\u5f71\u89c6\u6444\u5f71\u4e0e\u5236\u4f5c","special_type":"1","type_name":"\u672c\u79d1","level3_name":"\u620f\u5267\u4e0e\u5f71\u89c6\u5b66\u7c7b","level3_code":"123","level2_name":"\u827a\u672f\u5b66","level2_id":"14","level2_code":"13","code":"1303"},{"id":"171989","school_id":"2462","special_id":"339","nation_feature":"2","province_feature":"2","is_important":"2","limit_year":"\u56db\u5e74","year":"2022","level3_weight":"0","nation_first_class":"2","xueke_rank":"0","xueke_rank_score":"","ruanke_rank":"9999","ruanke_level":"","is_video":2,"special_name":"\u64ad\u97f3\u4e0e\u4e3b\u6301\u827a\u672f","special_type":"1","type_name":"\u672c\u79d1","level3_name":"\u620f\u5267\u4e0e\u5f71\u89c6\u5b66\u7c7b","level3_code":"123","level2_name":"\u827a\u672f\u5b66","level2_id":"14","level2_code":"13","code":"1303"},{"id":"171990","school_id":"2462","special_id":"347","nation_feature":"2","province_feature":"2","is_important":"2","limit_year":"\u56db\u5e74","year":"2022","level3_weight":"0","nation_first_class":"2","xueke_rank":"0","xueke_rank_score":"","ruanke_rank":"9999","ruanke_level":"","is_video":2,"special_name":"\u73af\u5883\u8bbe\u8ba1","special_type":"1","type_name":"\u672c\u79d1","level3_name":"\u8bbe\u8ba1\u5b66\u7c7b","level3_code":"125","level2_name":"\u827a\u672f\u5b66","level2_id":"14","level2_code":"13","code":"1305"},{"id":"1801215","school_id":"2462","special_id":"1283","nation_feature":"2","province_feature":"2","is_important":"2","limit_year":"\u56db\u5e74","year":"2022","level3_weight":"0","nation_first_class":"2","xueke_rank":"0","xueke_rank_score":"","ruanke_rank":"9999","ruanke_level":"","is_video":2,"special_name":"\u6570\u636e\u79d1\u5b66\u4e0e\u5927\u6570\u636e\u6280\u672f","special_type":"1","type_name":"\u672c\u79d1","level3_name":"\u8ba1\u7b97\u673a\u7c7b","level3_code":"71","level2_name":"\u5de5\u5b66","level2_id":"10","level2_code":"08","code":"0809"}],"2":[{"id":"159132","school_id":"2462","special_id":"974","nation_feature":"2","province_feature":"2","is_important":"2","limit_year":"\u4e09\u5e74","year":"2022","level3_weight":"0","nation_first_class":"2","xueke_rank":"0","xueke_rank_score":"","ruanke_rank":"9999","ruanke_level":"","is_video":2,"special_name":"\u65b0\u95fb\u91c7\u7f16\u4e0e\u5236\u4f5c","special_type":"2","type_name":"\u4e13\u79d1\uff08\u9ad8\u804c\uff09","level3_name":"\u5e7f\u64ad\u5f71\u89c6\u7c7b","level3_code":"210","level2_name":"\u65b0\u95fb\u4f20\u64ad\u5927\u7c7b","level2_id":"30","level2_code":"56","code":"5602"},{"id":"159133","school_id":"2462","special_id":"886","nation_feature":"2","province_feature":"2","is_important":"2","limit_year":"\u4e09\u5e74","year":"2022","level3_weight":"0","nation_first_class":"2","xueke_rank":"0","xueke_rank_score":"","ruanke_rank":"9999","ruanke_level":"","is_video":2,"special_name":"\u7535\u5b50\u5546\u52a1","special_type":"2","type_name":"\u4e13\u79d1\uff08\u9ad8\u804c\uff09","level3_name":"\u7535\u5b50\u5546\u52a1\u7c7b","level3_code":"200","level2_name":"\u8d22\u7ecf\u5546\u8d38\u5927\u7c7b","level2_id":"27","level2_code":"53","code":"5307"},{"id":"1791417","school_id":"2462","special_id":"979","nation_feature":"2","province_feature":"2","is_important":"2","limit_year":"\u4e09\u5e74","year":"2022","level3_weight":"0","nation_first_class":"2","xueke_rank":"0","xueke_rank_score":"","ruanke_rank":"9999","ruanke_level":"","is_video":2,"special_name":"\u5f71\u89c6\u7f16\u5bfc","special_type":"2","type_name":"\u4e13\u79d1\uff08\u9ad8\u804c\uff09","level3_name":"\u5e7f\u64ad\u5f71\u89c6\u7c7b","level3_code":"210","level2_name":"\u65b0\u95fb\u4f20\u64ad\u5927\u7c7b","level2_id":"30","level2_code":"56","code":"5602"},{"id":"1791418","school_id":"2462","special_id":"975","nation_feature":"2","province_feature":"2","is_important":"2","limit_year":"\u4e09\u5e74","year":"2022","level3_weight":"0","nation_first_class":"2","xueke_rank":"0","xueke_rank_score":"","ruanke_rank":"9999","ruanke_level":"","is_video":2,"special_name":"\u64ad\u97f3\u4e0e\u4e3b\u6301","special_type":"2","type_name":"\u4e13\u79d1\uff08\u9ad8\u804c\uff09","level3_name":"\u5e7f\u64ad\u5f71\u89c6\u7c7b","level3_code":"210","level2_name":"\u65b0\u95fb\u4f20\u64ad\u5927\u7c7b","level2_id":"30","level2_code":"56","code":"5602"},{"id":"1791419","school_id":"2462","special_id":"934","nation_feature":"2","province_feature":"2","is_important":"2","limit_year":"\u4e09\u5e74","year":"2022","level3_weight":"0","nation_first_class":"2","xueke_rank":"0","xueke_rank_score":"","ruanke_rank":"9999","ruanke_level":"","is_video":2,"special_name":"\u620f\u5267\u5f71\u89c6\u8868\u6f14","special_type":"2","type_name":"\u4e13\u79d1\uff08\u9ad8\u804c\uff09","level3_name":"\u8868\u6f14\u827a\u672f\u7c7b","level3_code":"206","level2_name":"\u6587\u5316\u827a\u672f\u5927\u7c7b","level2_id":"29","level2_code":"55","code":"5502"},{"id":"1791420","school_id":"2462","special_id":"982","nation_feature":"2","province_feature":"2","is_important":"2","limit_year":"\u4e09\u5e74","year":"2022","level3_weight":"0","nation_first_class":"2","xueke_rank":"0","xueke_rank_score":"","ruanke_rank":"9999","ruanke_level":"","is_video":2,"special_name":"\u5f71\u89c6\u52a8\u753b","special_type":"2","type_name":"\u4e13\u79d1\uff08\u9ad8\u804c\uff09","level3_name":"\u5e7f\u64ad\u5f71\u89c6\u7c7b","level3_code":"210","level2_name":"\u65b0\u95fb\u4f20\u64ad\u5927\u7c7b","level2_id":"30","level2_code":"56","code":"5602"}],"3":"","4":[]},"special":[{"level3_weight":"0","code":"0501","name":"\u4e2d\u56fd\u8bed\u8a00\u6587\u5b66\u7c7b(\u672c)","special":[{"id":"79470","school_id":"2462","special_id":"40","nation_feature":"2","province_feature":"2","is_important":"2","limit_year":"\u56db\u5e74","year":"2022","level3_weight":"0","nation_first_class":"2","xueke_rank":"0","xueke_rank_score":"","ruanke_rank":"9999","ruanke_level":"","is_video":2,"special_name":"\u6c49\u8bed\u8a00\u6587\u5b66","special_type":"1","type_name":"\u672c\u79d1","level3_name":"\u4e2d\u56fd\u8bed\u8a00\u6587\u5b66\u7c7b","level3_code":"47","level2_name":"\u6587\u5b66","level2_id":"7","level2_code":"05","code":"0501"}]},{"level3_weight":"0","code":"0502","name":"\u5916\u56fd\u8bed\u8a00\u6587\u5b66\u7c7b(\u672c)","special":[{"id":"79471","school_id":"2462","special_id":"45","nation_feature":"2","province_feature":"2","is_important":"2","limit_year":"\u56db\u5e74","year":"2022","level3_weight":"0","nation_first_class":"2","xueke_rank":"0","xueke_rank_score":"","ruanke_rank":"9999","ruanke_level":"","is_video":2,"special_name":"\u82f1\u8bed","special_type":"1","type_name":"\u672c\u79d1","level3_name":"\u5916\u56fd\u8bed\u8a00\u6587\u5b66\u7c7b","level3_code":"48","level2_name":"\u6587\u5b66","level2_id":"7","level2_code":"05","code":"0502"}]},{"level3_weight":"0","code":"0503","name":"\u65b0\u95fb\u4f20\u64ad\u5b66\u7c7b(\u672c)","special":[{"id":"79473","school_id":"2462","special_id":"110","nation_feature":"2","province_feature":"2","is_important":"2","limit_year":"\u56db\u5e74","year":"2022","level3_weight":"0","nation_first_class":"2","xueke_rank":"0","xueke_rank_score":"","ruanke_rank":"9999","ruanke_level":"","is_video":2,"special_name":"\u4f20\u64ad\u5b66","special_type":"1","type_name":"\u672c\u79d1","level3_name":"\u65b0\u95fb\u4f20\u64ad\u5b66\u7c7b","level3_code":"49","level2_name":"\u6587\u5b66","level2_id":"7","level2_code":"05","code":"0503"},{"id":"79472","school_id":"2462","special_id":"108","nation_feature":"2","province_feature":"2","is_important":"2","limit_year":"\u56db\u5e74","year":"2022","level3_weight":"0","nation_first_class":"2","xueke_rank":"0","xueke_rank_score":"","ruanke_rank":"9999","ruanke_level":"","is_video":2,"special_name":"\u5e7f\u64ad\u7535\u89c6\u5b66","special_type":"1","type_name":"\u672c\u79d1","level3_name":"\u65b0\u95fb\u4f20\u64ad\u5b66\u7c7b","level3_code":"49","level2_name":"\u6587\u5b66","level2_id":"7","level2_code":"05","code":"0503"},{"id":"159129","school_id":"2462","special_id":"1130","nation_feature":"2","province_feature":"2","is_important":"2","limit_year":"\u56db\u5e74","year":"2022","level3_weight":"0","nation_first_class":"2","xueke_rank":"0","xueke_rank_score":"","ruanke_rank":"9999","ruanke_level":"","is_video":2,"special_name":"\u7f51\u7edc\u4e0e\u65b0\u5a92\u4f53","special_type":"1","type_name":"\u672c\u79d1","level3_name":"\u65b0\u95fb\u4f20\u64ad\u5b66\u7c7b","level3_code":"49","level2_name":"\u6587\u5b66","level2_id":"7","level2_code":"05","code":"0503"},{"id":"159130","school_id":"2462","special_id":"109","nation_feature":"2","province_feature":"2","is_important":"2","limit_year":"\u56db\u5e74","year":"2022","level3_weight":"0","nation_first_class":"2","xueke_rank":"0","xueke_rank_score":"","ruanke_rank":"9999","ruanke_level":"","is_video":2,"special_name":"\u5e7f\u544a\u5b66","special_type":"1","type_name":"\u672c\u79d1","level3_name":"\u65b0\u95fb\u4f20\u64ad\u5b66\u7c7b","level3_code":"49","level2_name":"\u6587\u5b66","level2_id":"7","level2_code":"05","code":"0503"}]},{"level3_weight":"0","code":"0807","name":"\u7535\u5b50\u4fe1\u606f\u7c7b(\u672c)","special":[{"id":"79475","school_id":"2462","special_id":"165","nation_feature":"2","province_feature":"2","is_important":"2","limit_year":"\u56db\u5e74","year":"2022","level3_weight":"0","nation_first_class":"2","xueke_rank":"0","xueke_rank_score":"","ruanke_rank":"9999","ruanke_level":"","is_video":2,"special_name":"\u7535\u5b50\u4fe1\u606f\u5de5\u7a0b","special_type":"1","type_name":"\u672c\u79d1","level3_name":"\u7535\u5b50\u4fe1\u606f\u7c7b","level3_code":"69","level2_name":"\u5de5\u5b66","level2_id":"10","level2_code":"08","code":"0807"},{"id":"79465","school_id":"2462","special_id":"1157","nation_feature":"2","province_feature":"2","is_important":"2","limit_year":"\u56db\u5e74","year":"2022","level3_weight":"0","nation_first_class":"2","xueke_rank":"0","xueke_rank_score":"","ruanke_rank":"9999","ruanke_level":"","is_video":2,"special_name":"\u5e7f\u64ad\u7535\u89c6\u5de5\u7a0b","special_type":"1","type_name":"\u672c\u79d1","level3_name":"\u7535\u5b50\u4fe1\u606f\u7c7b","level3_code":"69","level2_name":"\u5de5\u5b66","level2_id":"10","level2_code":"08","code":"0807"}]},{"level3_weight":"0","code":"0809","name":"\u8ba1\u7b97\u673a\u7c7b(\u672c)","special":[{"id":"159134","school_id":"2462","special_id":"173","nation_feature":"2","province_feature":"2","is_important":"2","limit_year":"\u56db\u5e74","year":"2022","level3_weight":"0","nation_first_class":"2","xueke_rank":"0","xueke_rank_score":"","ruanke_rank":"9999","ruanke_level":"","is_video":2,"special_name":"\u8f6f\u4ef6\u5de5\u7a0b","special_type":"1","type_name":"\u672c\u79d1","level3_name":"\u8ba1\u7b97\u673a\u7c7b","level3_code":"71","level2_name":"\u5de5\u5b66","level2_id":"10","level2_code":"08","code":"0809"},{"id":"1801215","school_id":"2462","special_id":"1283","nation_feature":"2","province_feature":"2","is_important":"2","limit_year":"\u56db\u5e74","year":"2022","level3_weight":"0","nation_first_class":"2","xueke_rank":"0","xueke_rank_score":"","ruanke_rank":"9999","ruanke_level":"","is_video":2,"special_name":"\u6570\u636e\u79d1\u5b66\u4e0e\u5927\u6570\u636e\u6280\u672f","special_type":"1","type_name":"\u672c\u79d1","level3_name":"\u8ba1\u7b97\u673a\u7c7b","level3_code":"71","level2_name":"\u5de5\u5b66","level2_id":"10","level2_code":"08","code":"0809"}]},{"level3_weight":"0","code":"1202","name":"\u5de5\u5546\u7ba1\u7406\u7c7b(\u672c)","special":[{"id":"79476","school_id":"2462","special_id":"306","nation_feature":"2","province_feature":"2","is_important":"2","limit_year":"\u56db\u5e74","year":"2022","level3_weight":"0","nation_first_class":"2","xueke_rank":"0","xueke_rank_score":"","ruanke_rank":"9999","ruanke_level":"","is_video":2,"special_name":"\u6587\u5316\u4ea7\u4e1a\u7ba1\u7406","special_type":"1","type_name":"\u672c\u79d1","level3_name":"\u5de5\u5546\u7ba1\u7406\u7c7b","level3_code":"113","level2_name":"\u7ba1\u7406\u5b66","level2_id":"13","level2_code":"12","code":"1202"}]},{"level3_weight":"0","code":"1208","name":"\u7535\u5b50\u5546\u52a1\u7c7b(\u672c)","special":[{"id":"79468","school_id":"2462","special_id":"320","nation_feature":"2","province_feature":"2","is_important":"2","limit_year":"\u56db\u5e74","year":"2022","level3_weight":"0","nation_first_class":"2","xueke_rank":"0","xueke_rank_score":"","ruanke_rank":"9999","ruanke_level":"","is_video":2,"special_name":"\u7535\u5b50\u5546\u52a1","special_type":"1","type_name":"\u672c\u79d1","level3_name":"\u7535\u5b50\u5546\u52a1\u7c7b","level3_code":"119","level2_name":"\u7ba1\u7406\u5b66","level2_id":"13","level2_code":"12","code":"1208"}]},{"level3_weight":"0","code":"1209","name":"\u65c5\u6e38\u7ba1\u7406\u7c7b(\u672c)","special":[{"id":"159131","school_id":"2462","special_id":"323","nation_feature":"2","province_feature":"2","is_important":"2","limit_year":"\u56db\u5e74","year":"2022","level3_weight":"0","nation_first_class":"2","xueke_rank":"0","xueke_rank_score":"","ruanke_rank":"9999","ruanke_level":"","is_video":2,"special_name":"\u4f1a\u5c55\u7ecf\u6d4e\u4e0e\u7ba1\u7406","special_type":"1","type_name":"\u672c\u79d1","level3_name":"\u65c5\u6e38\u7ba1\u7406\u7c7b","level3_code":"120","level2_name":"\u7ba1\u7406\u5b66","level2_id":"13","level2_code":"12","code":"1209"}]},{"level3_weight":"0","code":"1302","name":"\u97f3\u4e50\u4e0e\u821e\u8e48\u5b66\u7c7b(\u672c)","special":[{"id":"761937","school_id":"2462","special_id":"325","nation_feature":"2","province_feature":"2","is_important":"2","limit_year":"\u56db\u5e74","year":"2022","level3_weight":"0","nation_first_class":"2","xueke_rank":"0","xueke_rank_score":"","ruanke_rank":"9999","ruanke_level":"","is_video":2,"special_name":"\u97f3\u4e50\u8868\u6f14","special_type":"1","type_name":"\u672c\u79d1","level3_name":"\u97f3\u4e50\u4e0e\u821e\u8e48\u5b66\u7c7b","level3_code":"122","level2_name":"\u827a\u672f\u5b66","level2_id":"14","level2_code":"13","code":"1302"},{"id":"761938","school_id":"2462","special_id":"326","nation_feature":"2","province_feature":"2","is_important":"2","limit_year":"\u4e94\u5e74","year":"2022","level3_weight":"0","nation_first_class":"2","xueke_rank":"0","xueke_rank_score":"","ruanke_rank":"9999","ruanke_level":"","is_video":2,"special_name":"\u97f3\u4e50\u5b66","special_type":"1","type_name":"\u672c\u79d1","level3_name":"\u97f3\u4e50\u4e0e\u821e\u8e48\u5b66\u7c7b","level3_code":"122","level2_name":"\u827a\u672f\u5b66","level2_id":"14","level2_code":"13","code":"1302"},{"id":"171985","school_id":"2462","special_id":"329","nation_feature":"2","province_feature":"2","is_important":"2","limit_year":"\u56db\u5e74","year":"2022","level3_weight":"0","nation_first_class":"2","xueke_rank":"0","xueke_rank_score":"","ruanke_rank":"9999","ruanke_level":"","is_video":2,"special_name":"\u821e\u8e48\u5b66","special_type":"1","type_name":"\u672c\u79d1","level3_name":"\u97f3\u4e50\u4e0e\u821e\u8e48\u5b66\u7c7b","level3_code":"122","level2_name":"\u827a\u672f\u5b66","level2_id":"14","level2_code":"13","code":"1302"}]},{"level3_weight":"0","code":"1303","name":"\u620f\u5267\u4e0e\u5f71\u89c6\u5b66\u7c7b(\u672c)","special":[{"id":"704575","school_id":"2462","special_id":"335","nation_feature":"2","province_feature":"2","is_important":"2","limit_year":"\u56db\u5e74","year":"2022","level3_weight":"0","nation_first_class":"2","xueke_rank":"0","xueke_rank_score":"","ruanke_rank":"9999","ruanke_level":"","is_video":2,"special_name":"\u5e7f\u64ad\u7535\u89c6\u7f16\u5bfc","special_type":"1","type_name":"\u672c\u79d1","level3_name":"\u620f\u5267\u4e0e\u5f71\u89c6\u5b66\u7c7b","level3_code":"123","level2_name":"\u827a\u672f\u5b66","level2_id":"14","level2_code":"13","code":"1303"},{"id":"1023066","school_id":"2462","special_id":"340","nation_feature":"2","province_feature":"2","is_important":"2","limit_year":"\u56db\u5e74","year":"2022","level3_weight":"0","nation_first_class":"2","xueke_rank":"0","xueke_rank_score":"","ruanke_rank":"9999","ruanke_level":"","is_video":2,"special_name":"\u52a8\u753b","special_type":"1","type_name":"\u672c\u79d1","level3_name":"\u620f\u5267\u4e0e\u5f71\u89c6\u5b66\u7c7b","level3_code":"123","level2_name":"\u827a\u672f\u5b66","level2_id":"14","level2_code":"13","code":"1303"},{"id":"1023068","school_id":"2462","special_id":"337","nation_feature":"2","province_feature":"2","is_important":"2","limit_year":"\u56db\u5e74","year":"2022","level3_weight":"0","nation_first_class":"2","xueke_rank":"0","xueke_rank_score":"","ruanke_rank":"9999","ruanke_level":"","is_video":2,"special_name":"\u620f\u5267\u5f71\u89c6\u7f8e\u672f\u8bbe\u8ba1","special_type":"1","type_name":"\u672c\u79d1","level3_name":"\u620f\u5267\u4e0e\u5f71\u89c6\u5b66\u7c7b","level3_code":"123","level2_name":"\u827a\u672f\u5b66","level2_id":"14","level2_code":"13","code":"1303"},{"id":"2012553","school_id":"2462","special_id":"8442","nation_feature":"2","province_feature":"2","is_important":"2","limit_year":"\u56db\u5e74","year":"2022","level3_weight":"0","nation_first_class":"2","xueke_rank":"0","xueke_rank_score":"","ruanke_rank":"9999","ruanke_level":"","is_video":2,"special_name":"\u620f\u5267\u6559\u80b2","special_type":"1","type_name":"\u672c\u79d1","level3_name":"\u620f\u5267\u4e0e\u5f71\u89c6\u5b66\u7c7b","level3_code":"123","level2_name":"\u827a\u672f\u5b66","level2_id":"14","level2_code":"13","code":"1303"},{"id":"1035938","school_id":"2462","special_id":"331","nation_feature":"2","province_feature":"2","is_important":"2","limit_year":"\u56db\u5e74","year":"2022","level3_weight":"0","nation_first_class":"2","xueke_rank":"0","xueke_rank_score":"","ruanke_rank":"9999","ruanke_level":"","is_video":2,"special_name":"\u8868\u6f14\uff08\u6f14\u827a\u4e3b\u6301)","special_type":"1","type_name":"\u672c\u79d1","level3_name":"\u620f\u5267\u4e0e\u5f71\u89c6\u5b66\u7c7b","level3_code":"123","level2_name":"\u827a\u672f\u5b66","level2_id":"14","level2_code":"13","code":"1303"},{"id":"171983","school_id":"2462","special_id":"334","nation_feature":"2","province_feature":"2","is_important":"2","limit_year":"\u56db\u5e74","year":"2022","level3_weight":"0","nation_first_class":"2","xueke_rank":"0","xueke_rank_score":"","ruanke_rank":"9999","ruanke_level":"","is_video":2,"special_name":"\u620f\u5267\u5f71\u89c6\u6587\u5b66","special_type":"1","type_name":"\u672c\u79d1","level3_name":"\u620f\u5267\u4e0e\u5f71\u89c6\u5b66\u7c7b","level3_code":"123","level2_name":"\u827a\u672f\u5b66","level2_id":"14","level2_code":"13","code":"1303"},{"id":"171984","school_id":"2462","special_id":"331","nation_feature":"2","province_feature":"2","is_important":"2","limit_year":"\u56db\u5e74","year":"2022","level3_weight":"0","nation_first_class":"2","xueke_rank":"0","xueke_rank_score":"","ruanke_rank":"9999","ruanke_level":"","is_video":2,"special_name":"\u8868\u6f14","special_type":"1","type_name":"\u672c\u79d1","level3_name":"\u620f\u5267\u4e0e\u5f71\u89c6\u5b66\u7c7b","level3_code":"123","level2_name":"\u827a\u672f\u5b66","level2_id":"14","level2_code":"13","code":"1303"},{"id":"171987","school_id":"2462","special_id":"336","nation_feature":"2","province_feature":"2","is_important":"2","limit_year":"\u56db\u5e74","year":"2022","level3_weight":"0","nation_first_class":"2","xueke_rank":"0","xueke_rank_score":"","ruanke_rank":"9999","ruanke_level":"","is_video":2,"special_name":"\u620f\u5267\u5f71\u89c6\u5bfc\u6f14","special_type":"1","type_name":"\u672c\u79d1","level3_name":"\u620f\u5267\u4e0e\u5f71\u89c6\u5b66\u7c7b","level3_code":"123","level2_name":"\u827a\u672f\u5b66","level2_id":"14","level2_code":"13","code":"1303"},{"id":"171988","school_id":"2462","special_id":"1248","nation_feature":"2","province_feature":"2","is_important":"2","limit_year":"\u56db\u5e74","year":"2022","level3_weight":"0","nation_first_class":"2","xueke_rank":"0","xueke_rank_score":"","ruanke_rank":"9999","ruanke_level":"","is_video":2,"special_name":"\u5f71\u89c6\u6444\u5f71\u4e0e\u5236\u4f5c","special_type":"1","type_name":"\u672c\u79d1","level3_name":"\u620f\u5267\u4e0e\u5f71\u89c6\u5b66\u7c7b","level3_code":"123","level2_name":"\u827a\u672f\u5b66","level2_id":"14","level2_code":"13","code":"1303"},{"id":"171989","school_id":"2462","special_id":"339","nation_feature":"2","province_feature":"2","is_important":"2","limit_year":"\u56db\u5e74","year":"2022","level3_weight":"0","nation_first_class":"2","xueke_rank":"0","xueke_rank_score":"","ruanke_rank":"9999","ruanke_level":"","is_video":2,"special_name":"\u64ad\u97f3\u4e0e\u4e3b\u6301\u827a\u672f","special_type":"1","type_name":"\u672c\u79d1","level3_name":"\u620f\u5267\u4e0e\u5f71\u89c6\u5b66\u7c7b","level3_code":"123","level2_name":"\u827a\u672f\u5b66","level2_id":"14","level2_code":"13","code":"1303"}]},{"level3_weight":"0","code":"1304","name":"\u7f8e\u672f\u5b66\u7c7b(\u672c)","special":[{"id":"171986","school_id":"2462","special_id":"344","nation_feature":"2","province_feature":"2","is_important":"2","limit_year":"\u56db\u5e74","year":"2022","level3_weight":"0","nation_first_class":"2","xueke_rank":"0","xueke_rank_score":"","ruanke_rank":"9999","ruanke_level":"","is_video":2,"special_name":"\u6444\u5f71","special_type":"1","type_name":"\u672c\u79d1","level3_name":"\u7f8e\u672f\u5b66\u7c7b","level3_code":"124","level2_name":"\u827a\u672f\u5b66","level2_id":"14","level2_code":"13","code":"1304"}]},{"level3_weight":"0","code":"1305","name":"\u8bbe\u8ba1\u5b66\u7c7b(\u672c)","special":[{"id":"704573","school_id":"2462","special_id":"346","nation_feature":"2","province_feature":"2","is_important":"2","limit_year":"\u56db\u5e74","year":"2022","level3_weight":"0","nation_first_class":"2","xueke_rank":"0","xueke_rank_score":"","ruanke_rank":"9999","ruanke_level":"","is_video":2,"special_name":"\u89c6\u89c9\u4f20\u8fbe\u8bbe\u8ba1","special_type":"1","type_name":"\u672c\u79d1","level3_name":"\u8bbe\u8ba1\u5b66\u7c7b","level3_code":"125","level2_name":"\u827a\u672f\u5b66","level2_id":"14","level2_code":"13","code":"1305"},{"id":"1023067","school_id":"2462","special_id":"352","nation_feature":"2","province_feature":"2","is_important":"2","limit_year":"\u56db\u5e74","year":"2022","level3_weight":"0","nation_first_class":"2","xueke_rank":"0","xueke_rank_score":"","ruanke_rank":"9999","ruanke_level":"","is_video":2,"special_name":"\u6570\u5b57\u5a92\u4f53\u827a\u672f","special_type":"1","type_name":"\u672c\u79d1","level3_name":"\u8bbe\u8ba1\u5b66\u7c7b","level3_code":"125","level2_name":"\u827a\u672f\u5b66","level2_id":"14","level2_code":"13","code":"1305"},{"id":"171990","school_id":"2462","special_id":"347","nation_feature":"2","province_feature":"2","is_important":"2","limit_year":"\u56db\u5e74","year":"2022","level3_weight":"0","nation_first_class":"2","xueke_rank":"0","xueke_rank_score":"","ruanke_rank":"9999","ruanke_level":"","is_video":2,"special_name":"\u73af\u5883\u8bbe\u8ba1","special_type":"1","type_name":"\u672c\u79d1","level3_name":"\u8bbe\u8ba1\u5b66\u7c7b","level3_code":"125","level2_name":"\u827a\u672f\u5b66","level2_id":"14","level2_code":"13","code":"1305"}]},{"level3_weight":"0","code":"5307","name":"\u7535\u5b50\u5546\u52a1\u7c7b(\u4e13)","special":[{"id":"159133","school_id":"2462","special_id":"886","nation_feature":"2","province_feature":"2","is_important":"2","limit_year":"\u4e09\u5e74","year":"2022","level3_weight":"0","nation_first_class":"2","xueke_rank":"0","xueke_rank_score":"","ruanke_rank":"9999","ruanke_level":"","is_video":2,"special_name":"\u7535\u5b50\u5546\u52a1","special_type":"2","type_name":"\u4e13\u79d1\uff08\u9ad8\u804c\uff09","level3_name":"\u7535\u5b50\u5546\u52a1\u7c7b","level3_code":"200","level2_name":"\u8d22\u7ecf\u5546\u8d38\u5927\u7c7b","level2_id":"27","level2_code":"53","code":"5307"}]},{"level3_weight":"0","code":"5502","name":"\u8868\u6f14\u827a\u672f\u7c7b(\u4e13)","special":[{"id":"1791419","school_id":"2462","special_id":"934","nation_feature":"2","province_feature":"2","is_important":"2","limit_year":"\u4e09\u5e74","year":"2022","level3_weight":"0","nation_first_class":"2","xueke_rank":"0","xueke_rank_score":"","ruanke_rank":"9999","ruanke_level":"","is_video":2,"special_name":"\u620f\u5267\u5f71\u89c6\u8868\u6f14","special_type":"2","type_name":"\u4e13\u79d1\uff08\u9ad8\u804c\uff09","level3_name":"\u8868\u6f14\u827a\u672f\u7c7b","level3_code":"206","level2_name":"\u6587\u5316\u827a\u672f\u5927\u7c7b","level2_id":"29","level2_code":"55","code":"5502"}]},{"level3_weight":"0","code":"5602","name":"\u5e7f\u64ad\u5f71\u89c6\u7c7b(\u4e13)","special":[{"id":"159132","school_id":"2462","special_id":"974","nation_feature":"2","province_feature":"2","is_important":"2","limit_year":"\u4e09\u5e74","year":"2022","level3_weight":"0","nation_first_class":"2","xueke_rank":"0","xueke_rank_score":"","ruanke_rank":"9999","ruanke_level":"","is_video":2,"special_name":"\u65b0\u95fb\u91c7\u7f16\u4e0e\u5236\u4f5c","special_type":"2","type_name":"\u4e13\u79d1\uff08\u9ad8\u804c\uff09","level3_name":"\u5e7f\u64ad\u5f71\u89c6\u7c7b","level3_code":"210","level2_name":"\u65b0\u95fb\u4f20\u64ad\u5927\u7c7b","level2_id":"30","level2_code":"56","code":"5602"},{"id":"1791417","school_id":"2462","special_id":"979","nation_feature":"2","province_feature":"2","is_important":"2","limit_year":"\u4e09\u5e74","year":"2022","level3_weight":"0","nation_first_class":"2","xueke_rank":"0","xueke_rank_score":"","ruanke_rank":"9999","ruanke_level":"","is_video":2,"special_name":"\u5f71\u89c6\u7f16\u5bfc","special_type":"2","type_name":"\u4e13\u79d1\uff08\u9ad8\u804c\uff09","level3_name":"\u5e7f\u64ad\u5f71\u89c6\u7c7b","level3_code":"210","level2_name":"\u65b0\u95fb\u4f20\u64ad\u5927\u7c7b","level2_id":"30","level2_code":"56","code":"5602"},{"id":"1791418","school_id":"2462","special_id":"975","nation_feature":"2","province_feature":"2","is_important":"2","limit_year":"\u4e09\u5e74","year":"2022","level3_weight":"0","nation_first_class":"2","xueke_rank":"0","xueke_rank_score":"","ruanke_rank":"9999","ruanke_level":"","is_video":2,"special_name":"\u64ad\u97f3\u4e0e\u4e3b\u6301","special_type":"2","type_name":"\u4e13\u79d1\uff08\u9ad8\u804c\uff09","level3_name":"\u5e7f\u64ad\u5f71\u89c6\u7c7b","level3_code":"210","level2_name":"\u65b0\u95fb\u4f20\u64ad\u5927\u7c7b","level2_id":"30","level2_code":"56","code":"5602"},{"id":"1791420","school_id":"2462","special_id":"982","nation_feature":"2","province_feature":"2","is_important":"2","limit_year":"\u4e09\u5e74","year":"2022","level3_weight":"0","nation_first_class":"2","xueke_rank":"0","xueke_rank_score":"","ruanke_rank":"9999","ruanke_level":"","is_video":2,"special_name":"\u5f71\u89c6\u52a8\u753b","special_type":"2","type_name":"\u4e13\u79d1\uff08\u9ad8\u804c\uff09","level3_name":"\u5e7f\u64ad\u5f71\u89c6\u7c7b","level3_code":"210","level2_name":"\u65b0\u95fb\u4f20\u64ad\u5927\u7c7b","level2_id":"30","level2_code":"56","code":"5602"}]}],"nation_feature":[],"educational_strength":{"num_doctor":"0","num_doctor2":"0","num_master":"0","num_master2":"0","num_subject":"0","gbh_num":"0","a_subject":"0","dualclass":0,"nation_feature":0}},"md5":"9e964a1338fc67801503d537c360268f","time":"2024-06-26 02:01:07"}