{"code":"0000","message":"\u6210\u529f","data":{"1":[{"id":"1036903","school_id":"2973","special_id":"212","nation_feature":"2","province_feature":"2","is_important":"2","limit_year":"\u56db\u5e74","year":"2022","level3_weight":"0","nation_first_class":"2","xueke_rank":"0","xueke_rank_score":"","ruanke_rank":"9999","ruanke_level":"","is_video":2,"special_name":"\u6b66\u5668\u7cfb\u7edf\u4e0e\u5de5\u7a0b","special_type":"1","type_name":"\u672c\u79d1","level3_name":"\u5175\u5668\u7c7b","level3_code":"83","level2_name":"\u5de5\u5b66","level2_id":"10","level2_code":"08","code":"0821"},{"id":"1036904","school_id":"2973","special_id":"217","nation_feature":"2","province_feature":"2","is_important":"2","limit_year":"\u56db\u5e74","year":"2022","level3_weight":"0","nation_first_class":"2","xueke_rank":"0","xueke_rank_score":"","ruanke_rank":"9999","ruanke_level":"","is_video":2,"special_name":"\u88c5\u7532\u8f66\u8f86\u5de5\u7a0b","special_type":"1","type_name":"\u672c\u79d1","level3_name":"\u5175\u5668\u7c7b","level3_code":"83","level2_name":"\u5de5\u5b66","level2_id":"10","level2_code":"08","code":"0821"},{"id":"1036905","school_id":"2973","special_id":"4203","nation_feature":"2","province_feature":"2","is_important":"2","limit_year":"\u56db\u5e74","year":"2022","level3_weight":"0","nation_first_class":"2","xueke_rank":"0","xueke_rank_score":"","ruanke_rank":"9999","ruanke_level":"","is_video":2,"special_name":"\u4f5c\u6218\u6307\u6325","special_type":"1","type_name":"\u672c\u79d1","level3_name":"\u5176\u4ed6","level3_code":"0","level2_name":"","level2_id":"0","level2_code":9999,"code":9999},{"id":"1036907","school_id":"2973","special_id":"4202","nation_feature":"2","province_feature":"2","is_important":"2","limit_year":"\u56db\u5e74","year":"2022","level3_weight":"0","nation_first_class":"2","xueke_rank":"0","xueke_rank_score":"","ruanke_rank":"9999","ruanke_level":"","is_video":2,"special_name":"\u6307\u6325\u4fe1\u606f\u7cfb\u7edf\u5de5\u7a0b","special_type":"1","type_name":"\u672c\u79d1","level3_name":"\u5176\u4ed6","level3_code":"0","level2_name":"","level2_id":"0","level2_code":9999,"code":9999}],"2":"","special_detail":{"1":[{"id":"1036903","school_id":"2973","special_id":"212","nation_feature":"2","province_feature":"2","is_important":"2","limit_year":"\u56db\u5e74","year":"2022","level3_weight":"0","nation_first_class":"2","xueke_rank":"0","xueke_rank_score":"","ruanke_rank":"9999","ruanke_level":"","is_video":2,"special_name":"\u6b66\u5668\u7cfb\u7edf\u4e0e\u5de5\u7a0b","special_type":"1","type_name":"\u672c\u79d1","level3_name":"\u5175\u5668\u7c7b","level3_code":"83","level2_name":"\u5de5\u5b66","level2_id":"10","level2_code":"08","code":"0821"},{"id":"1036904","school_id":"2973","special_id":"217","nation_feature":"2","province_feature":"2","is_important":"2","limit_year":"\u56db\u5e74","year":"2022","level3_weight":"0","nation_first_class":"2","xueke_rank":"0","xueke_rank_score":"","ruanke_rank":"9999","ruanke_level":"","is_video":2,"special_name":"\u88c5\u7532\u8f66\u8f86\u5de5\u7a0b","special_type":"1","type_name":"\u672c\u79d1","level3_name":"\u5175\u5668\u7c7b","level3_code":"83","level2_name":"\u5de5\u5b66","level2_id":"10","level2_code":"08","code":"0821"},{"id":"1036905","school_id":"2973","special_id":"4203","nation_feature":"2","province_feature":"2","is_important":"2","limit_year":"\u56db\u5e74","year":"2022","level3_weight":"0","nation_first_class":"2","xueke_rank":"0","xueke_rank_score":"","ruanke_rank":"9999","ruanke_level":"","is_video":2,"special_name":"\u4f5c\u6218\u6307\u6325","special_type":"1","type_name":"\u672c\u79d1","level3_name":"\u5176\u4ed6","level3_code":"0","level2_name":"","level2_id":"0","level2_code":9999,"code":9999},{"id":"1036907","school_id":"2973","special_id":"4202","nation_feature":"2","province_feature":"2","is_important":"2","limit_year":"\u56db\u5e74","year":"2022","level3_weight":"0","nation_first_class":"2","xueke_rank":"0","xueke_rank_score":"","ruanke_rank":"9999","ruanke_level":"","is_video":2,"special_name":"\u6307\u6325\u4fe1\u606f\u7cfb\u7edf\u5de5\u7a0b","special_type":"1","type_name":"\u672c\u79d1","level3_name":"\u5176\u4ed6","level3_code":"0","level2_name":"","level2_id":"0","level2_code":9999,"code":9999}],"2":[],"3":"","4":[]},"special":[{"level3_weight":"0","code":"0821","name":"\u5175\u5668\u7c7b(\u672c)","special":[{"id":"1036903","school_id":"2973","special_id":"212","nation_feature":"2","province_feature":"2","is_important":"2","limit_year":"\u56db\u5e74","year":"2022","level3_weight":"0","nation_first_class":"2","xueke_rank":"0","xueke_rank_score":"","ruanke_rank":"9999","ruanke_level":"","is_video":2,"special_name":"\u6b66\u5668\u7cfb\u7edf\u4e0e\u5de5\u7a0b","special_type":"1","type_name":"\u672c\u79d1","level3_name":"\u5175\u5668\u7c7b","level3_code":"83","level2_name":"\u5de5\u5b66","level2_id":"10","level2_code":"08","code":"0821"},{"id":"1036904","school_id":"2973","special_id":"217","nation_feature":"2","province_feature":"2","is_important":"2","limit_year":"\u56db\u5e74","year":"2022","level3_weight":"0","nation_first_class":"2","xueke_rank":"0","xueke_rank_score":"","ruanke_rank":"9999","ruanke_level":"","is_video":2,"special_name":"\u88c5\u7532\u8f66\u8f86\u5de5\u7a0b","special_type":"1","type_name":"\u672c\u79d1","level3_name":"\u5175\u5668\u7c7b","level3_code":"83","level2_name":"\u5de5\u5b66","level2_id":"10","level2_code":"08","code":"0821"}]},{"level3_weight":"0","code":9999,"name":"\u5176\u4ed6(\u672c)","special":[{"id":"1036905","school_id":"2973","special_id":"4203","nation_feature":"2","province_feature":"2","is_important":"2","limit_year":"\u56db\u5e74","year":"2022","level3_weight":"0","nation_first_class":"2","xueke_rank":"0","xueke_rank_score":"","ruanke_rank":"9999","ruanke_level":"","is_video":2,"special_name":"\u4f5c\u6218\u6307\u6325","special_type":"1","type_name":"\u672c\u79d1","level3_name":"\u5176\u4ed6","level3_code":"0","level2_name":"","level2_id":"0","level2_code":9999,"code":9999},{"id":"1036907","school_id":"2973","special_id":"4202","nation_feature":"2","province_feature":"2","is_important":"2","limit_year":"\u56db\u5e74","year":"2022","level3_weight":"0","nation_first_class":"2","xueke_rank":"0","xueke_rank_score":"","ruanke_rank":"9999","ruanke_level":"","is_video":2,"special_name":"\u6307\u6325\u4fe1\u606f\u7cfb\u7edf\u5de5\u7a0b","special_type":"1","type_name":"\u672c\u79d1","level3_name":"\u5176\u4ed6","level3_code":"0","level2_name":"","level2_id":"0","level2_code":9999,"code":9999}]}],"nation_feature":[],"educational_strength":{"num_doctor":"2","num_doctor2":"0","num_master":"0","num_master2":"0","num_subject":"0","gbh_num":"0","a_subject":"0","dualclass":0,"nation_feature":0}},"md5":"cfcbb1f08f6dd7bbec94f057a54ce9a2","time":"2024-06-19 15:49:04"}