{"code":"0000","message":"\u6210\u529f","data":{"1":[{"id":"20557","school_id":"394","special_id":"164","nation_feature":"1","province_feature":"1","is_important":"2","limit_year":"\u56db\u5e74","year":"2022","level3_weight":"0","nation_first_class":"2","xueke_rank":"0","xueke_rank_score":"","ruanke_rank":"179","ruanke_level":"B","is_video":1,"special_name":"\u7535\u6c14\u5de5\u7a0b\u53ca\u5176\u81ea\u52a8\u5316","special_type":"1","type_name":"\u672c\u79d1","level3_name":"\u7535\u6c14\u7c7b","level3_code":"68","level2_name":"\u5de5\u5b66","level2_id":"10","level2_code":"08","code":"0806"},{"id":"20552","school_id":"394","special_id":"147","nation_feature":"1","province_feature":"1","is_important":"2","limit_year":"\u56db\u5e74","year":"2022","level3_weight":"0","nation_first_class":"2","xueke_rank":"0","xueke_rank_score":"","ruanke_rank":"245","ruanke_level":"B","is_video":2,"special_name":"\u673a\u68b0\u8bbe\u8ba1\u5236\u9020\u53ca\u5176\u81ea\u52a8\u5316","special_type":"1","type_name":"\u672c\u79d1","level3_name":"\u673a\u68b0\u7c7b","level3_code":"64","level2_name":"\u5de5\u5b66","level2_id":"10","level2_code":"08","code":"0802"},{"id":"20612","school_id":"394","special_id":"181","nation_feature":"2","province_feature":"2","is_important":"2","limit_year":"\u56db\u5e74","year":"2022","level3_weight":"0","nation_first_class":"2","xueke_rank":"0","xueke_rank_score":"","ruanke_rank":"42","ruanke_level":"B","is_video":2,"special_name":"\u5efa\u7b51\u7535\u6c14\u4e0e\u667a\u80fd\u5316","special_type":"1","type_name":"\u672c\u79d1","level3_name":"\u571f\u6728\u7c7b","level3_code":"72","level2_name":"\u5de5\u5b66","level2_id":"10","level2_code":"08","code":"0810"},{"id":"20606","school_id":"394","special_id":"183","nation_feature":"2","province_feature":"2","is_important":"2","limit_year":"\u56db\u5e74","year":"2022","level3_weight":"0","nation_first_class":"2","xueke_rank":"0","xueke_rank_score":"","ruanke_rank":"9999","ruanke_level":"","is_video":2,"special_name":"\u6c34\u6587\u4e0e\u6c34\u8d44\u6e90\u5de5\u7a0b","special_type":"1","type_name":"\u672c\u79d1","level3_name":"\u6c34\u5229\u7c7b","level3_code":"73","level2_name":"\u5de5\u5b66","level2_id":"10","level2_code":"08","code":"0811"},{"id":"20605","school_id":"394","special_id":"1147","nation_feature":"2","province_feature":"2","is_important":"2","limit_year":"\u56db\u5e74","year":"2022","level3_weight":"0","nation_first_class":"2","xueke_rank":"0","xueke_rank_score":"","ruanke_rank":"9999","ruanke_level":"","is_video":2,"special_name":"\u5b9d\u77f3\u53ca\u6750\u6599\u5de5\u827a\u5b66","special_type":"1","type_name":"\u672c\u79d1","level3_name":"\u6750\u6599\u7c7b","level3_code":"66","level2_name":"\u5de5\u5b66","level2_id":"10","level2_code":"08","code":"0804"},{"id":"20567","school_id":"394","special_id":"227","nation_feature":"2","province_feature":"2","is_important":"2","limit_year":"\u56db\u5e74","year":"2022","level3_weight":"0","nation_first_class":"2","xueke_rank":"0","xueke_rank_score":"","ruanke_rank":"9999","ruanke_level":"","is_video":2,"special_name":"\u519c\u4e1a\u6c34\u5229\u5de5\u7a0b","special_type":"1","type_name":"\u672c\u79d1","level3_name":"\u519c\u4e1a\u5de5\u7a0b\u7c7b","level3_code":"85","level2_name":"\u5de5\u5b66","level2_id":"10","level2_code":"08","code":"0823"},{"id":"20564","school_id":"394","special_id":"241","nation_feature":"2","province_feature":"2","is_important":"2","limit_year":"\u4e94\u5e74","year":"2022","level3_weight":"0","nation_first_class":"2","xueke_rank":"0","xueke_rank_score":"","ruanke_rank":"9999","ruanke_level":"","is_video":1,"special_name":"\u5efa\u7b51\u5b66","special_type":"1","type_name":"\u672c\u79d1","level3_name":"\u5efa\u7b51\u7c7b","level3_code":"90","level2_name":"\u5de5\u5b66","level2_id":"10","level2_code":"08","code":"0828"},{"id":"20563","school_id":"394","special_id":"178","nation_feature":"2","province_feature":"1","is_important":"2","limit_year":"\u56db\u5e74","year":"2022","level3_weight":"0","nation_first_class":"2","xueke_rank":"0","xueke_rank_score":"","ruanke_rank":"215","ruanke_level":"B","is_video":2,"special_name":"\u571f\u6728\u5de5\u7a0b","special_type":"1","type_name":"\u672c\u79d1","level3_name":"\u571f\u6728\u7c7b","level3_code":"72","level2_name":"\u5de5\u5b66","level2_id":"10","level2_code":"08","code":"0810"},{"id":"20561","school_id":"394","special_id":"165","nation_feature":"2","province_feature":"2","is_important":"2","limit_year":"\u56db\u5e74","year":"2022","level3_weight":"0","nation_first_class":"2","xueke_rank":"0","xueke_rank_score":"","ruanke_rank":"9999","ruanke_level":"","is_video":1,"special_name":"\u7535\u5b50\u4fe1\u606f\u5de5\u7a0b","special_type":"1","type_name":"\u672c\u79d1","level3_name":"\u7535\u5b50\u4fe1\u606f\u7c7b","level3_code":"69","level2_name":"\u5de5\u5b66","level2_id":"10","level2_code":"08","code":"0807"},{"id":"20559","school_id":"394","special_id":"171","nation_feature":"2","province_feature":"2","is_important":"2","limit_year":"\u56db\u5e74","year":"2022","level3_weight":"0","nation_first_class":"2","xueke_rank":"0","xueke_rank_score":"","ruanke_rank":"9999","ruanke_level":"","is_video":2,"special_name":"\u81ea\u52a8\u5316","special_type":"1","type_name":"\u672c\u79d1","level3_name":"\u81ea\u52a8\u5316\u7c7b","level3_code":"70","level2_name":"\u5de5\u5b66","level2_id":"10","level2_code":"08","code":"0808"},{"id":"20556","school_id":"394","special_id":"172","nation_feature":"2","province_feature":"2","is_important":"2","limit_year":"\u56db\u5e74","year":"2022","level3_weight":"0","nation_first_class":"2","xueke_rank":"0","xueke_rank_score":"","ruanke_rank":"9999","ruanke_level":"","is_video":1,"special_name":"\u8ba1\u7b97\u673a\u79d1\u5b66\u4e0e\u6280\u672f","special_type":"1","type_name":"\u672c\u79d1","level3_name":"\u8ba1\u7b97\u673a\u7c7b","level3_code":"71","level2_name":"\u5de5\u5b66","level2_id":"10","level2_code":"08","code":"0809"},{"id":"20555","school_id":"394","special_id":"148","nation_feature":"2","province_feature":"2","is_important":"2","limit_year":"\u56db\u5e74","year":"2022","level3_weight":"0","nation_first_class":"2","xueke_rank":"0","xueke_rank_score":"","ruanke_rank":"9999","ruanke_level":"","is_video":2,"special_name":"\u6750\u6599\u6210\u578b\u53ca\u63a7\u5236\u5de5\u7a0b","special_type":"1","type_name":"\u672c\u79d1","level3_name":"\u673a\u68b0\u7c7b","level3_code":"64","level2_name":"\u5de5\u5b66","level2_id":"10","level2_code":"08","code":"0802"},{"id":"20551","school_id":"394","special_id":"189","nation_feature":"2","province_feature":"2","is_important":"2","limit_year":"\u56db\u5e74","year":"2022","level3_weight":"0","nation_first_class":"2","xueke_rank":"0","xueke_rank_score":"","ruanke_rank":"9999","ruanke_level":"","is_video":2,"special_name":"\u5730\u8d28\u5de5\u7a0b","special_type":"1","type_name":"\u672c\u79d1","level3_name":"\u5730\u8d28\u7c7b","level3_code":"76","level2_name":"\u5de5\u5b66","level2_id":"10","level2_code":"08","code":"0814"},{"id":"20550","school_id":"394","special_id":"122","nation_feature":"2","province_feature":"2","is_important":"2","limit_year":"\u56db\u5e74","year":"2022","level3_weight":"0","nation_first_class":"2","xueke_rank":"0","xueke_rank_score":"","ruanke_rank":"9999","ruanke_level":"","is_video":2,"special_name":"\u5e94\u7528\u5316\u5b66","special_type":"1","type_name":"\u672c\u79d1","level3_name":"\u5316\u5b66\u7c7b","level3_code":"53","level2_name":"\u7406\u5b66","level2_id":"9","level2_code":"07","code":"0703"},{"id":"20568","school_id":"394","special_id":"182","nation_feature":"2","province_feature":"1","is_important":"2","limit_year":"\u56db\u5e74","year":"2022","level3_weight":"0","nation_first_class":"2","xueke_rank":"0","xueke_rank_score":"","ruanke_rank":"9999","ruanke_level":"","is_video":2,"special_name":"\u6c34\u5229\u6c34\u7535\u5de5\u7a0b","special_type":"1","type_name":"\u672c\u79d1","level3_name":"\u6c34\u5229\u7c7b","level3_code":"73","level2_name":"\u5de5\u5b66","level2_id":"10","level2_code":"08","code":"0811"}],"2":[{"id":"20609","school_id":"394","special_id":"784","nation_feature":"2","province_feature":"2","is_important":"2","limit_year":"\u4e09\u5e74","year":"2022","level3_weight":"0","nation_first_class":"2","xueke_rank":"0","xueke_rank_score":"","ruanke_rank":"9999","ruanke_level":"","is_video":2,"special_name":"\u8ba1\u7b97\u673a\u7f51\u7edc\u6280\u672f","special_type":"2","type_name":"\u4e13\u79d1\uff08\u9ad8\u804c\uff09","level3_name":"\u8ba1\u7b97\u673a\u7c7b","level3_code":"183","level2_name":"\u7535\u5b50\u4e0e\u4fe1\u606f\u5927\u7c7b","level2_id":"25","level2_code":"51","code":"5102"},{"id":"20611","school_id":"394","special_id":"886","nation_feature":"2","province_feature":"2","is_important":"2","limit_year":"\u4e09\u5e74","year":"2022","level3_weight":"0","nation_first_class":"2","xueke_rank":"0","xueke_rank_score":"","ruanke_rank":"9999","ruanke_level":"","is_video":2,"special_name":"\u7535\u5b50\u5546\u52a1","special_type":"2","type_name":"\u4e13\u79d1\uff08\u9ad8\u804c\uff09","level3_name":"\u7535\u5b50\u5546\u52a1\u7c7b","level3_code":"200","level2_name":"\u8d22\u7ecf\u5546\u8d38\u5927\u7c7b","level2_id":"27","level2_code":"53","code":"5307"},{"id":"20569","school_id":"394","special_id":"556","nation_feature":"2","province_feature":"2","is_important":"2","limit_year":"\u4e09\u5e74","year":"2022","level3_weight":"0","nation_first_class":"2","xueke_rank":"0","xueke_rank_score":"","ruanke_rank":"9999","ruanke_level":"","is_video":2,"special_name":"\u6c34\u5229\u6c34\u7535\u5efa\u7b51\u5de5\u7a0b","special_type":"2","type_name":"\u4e13\u79d1\uff08\u9ad8\u804c\uff09","level3_name":"\u6c34\u5229\u5de5\u7a0b\u4e0e\u7ba1\u7406\u7c7b","level3_code":"154","level2_name":"\u6c34\u5229\u5927\u7c7b","level2_id":"19","level2_code":"45","code":"4502"},{"id":"20560","school_id":"394","special_id":"469","nation_feature":"2","province_feature":"2","is_important":"2","limit_year":"\u4e09\u5e74","year":"2022","level3_weight":"0","nation_first_class":"2","xueke_rank":"0","xueke_rank_score":"","ruanke_rank":"9999","ruanke_level":"","is_video":2,"special_name":"\u53d1\u7535\u5382\u53ca\u7535\u529b\u7cfb\u7edf","special_type":"2","type_name":"\u4e13\u79d1\uff08\u9ad8\u804c\uff09","level3_name":"\u7535\u529b\u6280\u672f\u7c7b","level3_code":"139","level2_name":"\u80fd\u6e90\u52a8\u529b\u4e0e\u6750\u6599\u5927\u7c7b","level2_id":"17","level2_code":"43","code":"4301"},{"id":"1790246","school_id":"394","special_id":"8982","nation_feature":"2","province_feature":"2","is_important":"2","limit_year":"\u4e09\u5e74","year":"2022","level3_weight":"0","nation_first_class":"2","xueke_rank":"0","xueke_rank_score":"","ruanke_rank":"9999","ruanke_level":"","is_video":2,"special_name":"\u6c34\u7535\u7ad9\u8bbe\u5907\u5b89\u88c5\u4e0e\u7ba1\u7406","special_type":"2","type_name":"\u4e13\u79d1\uff08\u9ad8\u804c\uff09","level3_name":"\u6c34\u5229\u6c34\u7535\u8bbe\u5907\u7c7b","level3_code":"155","level2_name":"\u6c34\u5229\u5927\u7c7b","level2_id":"19","level2_code":"45","code":"4503"},{"id":"1790247","school_id":"394","special_id":"8990","nation_feature":"2","province_feature":"2","is_important":"2","limit_year":"\u4e09\u5e74","year":"2022","level3_weight":"0","nation_first_class":"2","xueke_rank":"0","xueke_rank_score":"","ruanke_rank":"9999","ruanke_level":"","is_video":2,"special_name":"\u667a\u80fd\u710a\u63a5\u6280\u672f","special_type":"2","type_name":"\u4e13\u79d1\uff08\u9ad8\u804c\uff09","level3_name":"\u673a\u68b0\u8bbe\u8ba1\u5236\u9020\u7c7b","level3_code":"157","level2_name":"\u88c5\u5907\u5236\u9020\u5927\u7c7b","level2_id":"20","level2_code":"46","code":"4601"},{"id":"1790248","school_id":"394","special_id":"9161","nation_feature":"2","province_feature":"2","is_important":"2","limit_year":"\u4e09\u5e74","year":"2022","level3_weight":"0","nation_first_class":"2","xueke_rank":"0","xueke_rank_score":"","ruanke_rank":"9999","ruanke_level":"","is_video":2,"special_name":"\u673a\u68b0\u5236\u9020\u53ca\u81ea\u52a8\u5316","special_type":"2","type_name":"\u4e13\u79d1\uff08\u9ad8\u804c\uff09","level3_name":"\u673a\u68b0\u8bbe\u8ba1\u5236\u9020\u7c7b","level3_code":"157","level2_name":"\u88c5\u5907\u5236\u9020\u5927\u7c7b","level2_id":"20","level2_code":"46","code":"4601"},{"id":"1790249","school_id":"394","special_id":"9176","nation_feature":"2","province_feature":"2","is_important":"2","limit_year":"\u4e09\u5e74","year":"2022","level3_weight":"0","nation_first_class":"2","xueke_rank":"0","xueke_rank_score":"","ruanke_rank":"9999","ruanke_level":"","is_video":2,"special_name":"\u6570\u5b57\u5a92\u4f53\u6280\u672f","special_type":"2","type_name":"\u4e13\u79d1\uff08\u9ad8\u804c\uff09","level3_name":"\u8ba1\u7b97\u673a\u7c7b","level3_code":"183","level2_name":"\u7535\u5b50\u4e0e\u4fe1\u606f\u5927\u7c7b","level2_id":"25","level2_code":"51","code":"5102"}],"special_detail":{"1":[{"id":"20557","school_id":"394","special_id":"164","nation_feature":"1","province_feature":"1","is_important":"2","limit_year":"\u56db\u5e74","year":"2022","level3_weight":"0","nation_first_class":"2","xueke_rank":"0","xueke_rank_score":"","ruanke_rank":"179","ruanke_level":"B","is_video":1,"special_name":"\u7535\u6c14\u5de5\u7a0b\u53ca\u5176\u81ea\u52a8\u5316","special_type":"1","type_name":"\u672c\u79d1","level3_name":"\u7535\u6c14\u7c7b","level3_code":"68","level2_name":"\u5de5\u5b66","level2_id":"10","level2_code":"08","code":"0806"},{"id":"20552","school_id":"394","special_id":"147","nation_feature":"1","province_feature":"1","is_important":"2","limit_year":"\u56db\u5e74","year":"2022","level3_weight":"0","nation_first_class":"2","xueke_rank":"0","xueke_rank_score":"","ruanke_rank":"245","ruanke_level":"B","is_video":2,"special_name":"\u673a\u68b0\u8bbe\u8ba1\u5236\u9020\u53ca\u5176\u81ea\u52a8\u5316","special_type":"1","type_name":"\u672c\u79d1","level3_name":"\u673a\u68b0\u7c7b","level3_code":"64","level2_name":"\u5de5\u5b66","level2_id":"10","level2_code":"08","code":"0802"},{"id":"20612","school_id":"394","special_id":"181","nation_feature":"2","province_feature":"2","is_important":"2","limit_year":"\u56db\u5e74","year":"2022","level3_weight":"0","nation_first_class":"2","xueke_rank":"0","xueke_rank_score":"","ruanke_rank":"42","ruanke_level":"B","is_video":2,"special_name":"\u5efa\u7b51\u7535\u6c14\u4e0e\u667a\u80fd\u5316","special_type":"1","type_name":"\u672c\u79d1","level3_name":"\u571f\u6728\u7c7b","level3_code":"72","level2_name":"\u5de5\u5b66","level2_id":"10","level2_code":"08","code":"0810"},{"id":"20606","school_id":"394","special_id":"183","nation_feature":"2","province_feature":"2","is_important":"2","limit_year":"\u56db\u5e74","year":"2022","level3_weight":"0","nation_first_class":"2","xueke_rank":"0","xueke_rank_score":"","ruanke_rank":"9999","ruanke_level":"","is_video":2,"special_name":"\u6c34\u6587\u4e0e\u6c34\u8d44\u6e90\u5de5\u7a0b","special_type":"1","type_name":"\u672c\u79d1","level3_name":"\u6c34\u5229\u7c7b","level3_code":"73","level2_name":"\u5de5\u5b66","level2_id":"10","level2_code":"08","code":"0811"},{"id":"20605","school_id":"394","special_id":"1147","nation_feature":"2","province_feature":"2","is_important":"2","limit_year":"\u56db\u5e74","year":"2022","level3_weight":"0","nation_first_class":"2","xueke_rank":"0","xueke_rank_score":"","ruanke_rank":"9999","ruanke_level":"","is_video":2,"special_name":"\u5b9d\u77f3\u53ca\u6750\u6599\u5de5\u827a\u5b66","special_type":"1","type_name":"\u672c\u79d1","level3_name":"\u6750\u6599\u7c7b","level3_code":"66","level2_name":"\u5de5\u5b66","level2_id":"10","level2_code":"08","code":"0804"},{"id":"20567","school_id":"394","special_id":"227","nation_feature":"2","province_feature":"2","is_important":"2","limit_year":"\u56db\u5e74","year":"2022","level3_weight":"0","nation_first_class":"2","xueke_rank":"0","xueke_rank_score":"","ruanke_rank":"9999","ruanke_level":"","is_video":2,"special_name":"\u519c\u4e1a\u6c34\u5229\u5de5\u7a0b","special_type":"1","type_name":"\u672c\u79d1","level3_name":"\u519c\u4e1a\u5de5\u7a0b\u7c7b","level3_code":"85","level2_name":"\u5de5\u5b66","level2_id":"10","level2_code":"08","code":"0823"},{"id":"20564","school_id":"394","special_id":"241","nation_feature":"2","province_feature":"2","is_important":"2","limit_year":"\u4e94\u5e74","year":"2022","level3_weight":"0","nation_first_class":"2","xueke_rank":"0","xueke_rank_score":"","ruanke_rank":"9999","ruanke_level":"","is_video":1,"special_name":"\u5efa\u7b51\u5b66","special_type":"1","type_name":"\u672c\u79d1","level3_name":"\u5efa\u7b51\u7c7b","level3_code":"90","level2_name":"\u5de5\u5b66","level2_id":"10","level2_code":"08","code":"0828"},{"id":"20563","school_id":"394","special_id":"178","nation_feature":"2","province_feature":"1","is_important":"2","limit_year":"\u56db\u5e74","year":"2022","level3_weight":"0","nation_first_class":"2","xueke_rank":"0","xueke_rank_score":"","ruanke_rank":"215","ruanke_level":"B","is_video":2,"special_name":"\u571f\u6728\u5de5\u7a0b","special_type":"1","type_name":"\u672c\u79d1","level3_name":"\u571f\u6728\u7c7b","level3_code":"72","level2_name":"\u5de5\u5b66","level2_id":"10","level2_code":"08","code":"0810"},{"id":"20561","school_id":"394","special_id":"165","nation_feature":"2","province_feature":"2","is_important":"2","limit_year":"\u56db\u5e74","year":"2022","level3_weight":"0","nation_first_class":"2","xueke_rank":"0","xueke_rank_score":"","ruanke_rank":"9999","ruanke_level":"","is_video":1,"special_name":"\u7535\u5b50\u4fe1\u606f\u5de5\u7a0b","special_type":"1","type_name":"\u672c\u79d1","level3_name":"\u7535\u5b50\u4fe1\u606f\u7c7b","level3_code":"69","level2_name":"\u5de5\u5b66","level2_id":"10","level2_code":"08","code":"0807"},{"id":"20559","school_id":"394","special_id":"171","nation_feature":"2","province_feature":"2","is_important":"2","limit_year":"\u56db\u5e74","year":"2022","level3_weight":"0","nation_first_class":"2","xueke_rank":"0","xueke_rank_score":"","ruanke_rank":"9999","ruanke_level":"","is_video":2,"special_name":"\u81ea\u52a8\u5316","special_type":"1","type_name":"\u672c\u79d1","level3_name":"\u81ea\u52a8\u5316\u7c7b","level3_code":"70","level2_name":"\u5de5\u5b66","level2_id":"10","level2_code":"08","code":"0808"},{"id":"20556","school_id":"394","special_id":"172","nation_feature":"2","province_feature":"2","is_important":"2","limit_year":"\u56db\u5e74","year":"2022","level3_weight":"0","nation_first_class":"2","xueke_rank":"0","xueke_rank_score":"","ruanke_rank":"9999","ruanke_level":"","is_video":1,"special_name":"\u8ba1\u7b97\u673a\u79d1\u5b66\u4e0e\u6280\u672f","special_type":"1","type_name":"\u672c\u79d1","level3_name":"\u8ba1\u7b97\u673a\u7c7b","level3_code":"71","level2_name":"\u5de5\u5b66","level2_id":"10","level2_code":"08","code":"0809"},{"id":"20555","school_id":"394","special_id":"148","nation_feature":"2","province_feature":"2","is_important":"2","limit_year":"\u56db\u5e74","year":"2022","level3_weight":"0","nation_first_class":"2","xueke_rank":"0","xueke_rank_score":"","ruanke_rank":"9999","ruanke_level":"","is_video":2,"special_name":"\u6750\u6599\u6210\u578b\u53ca\u63a7\u5236\u5de5\u7a0b","special_type":"1","type_name":"\u672c\u79d1","level3_name":"\u673a\u68b0\u7c7b","level3_code":"64","level2_name":"\u5de5\u5b66","level2_id":"10","level2_code":"08","code":"0802"},{"id":"20551","school_id":"394","special_id":"189","nation_feature":"2","province_feature":"2","is_important":"2","limit_year":"\u56db\u5e74","year":"2022","level3_weight":"0","nation_first_class":"2","xueke_rank":"0","xueke_rank_score":"","ruanke_rank":"9999","ruanke_level":"","is_video":2,"special_name":"\u5730\u8d28\u5de5\u7a0b","special_type":"1","type_name":"\u672c\u79d1","level3_name":"\u5730\u8d28\u7c7b","level3_code":"76","level2_name":"\u5de5\u5b66","level2_id":"10","level2_code":"08","code":"0814"},{"id":"20550","school_id":"394","special_id":"122","nation_feature":"2","province_feature":"2","is_important":"2","limit_year":"\u56db\u5e74","year":"2022","level3_weight":"0","nation_first_class":"2","xueke_rank":"0","xueke_rank_score":"","ruanke_rank":"9999","ruanke_level":"","is_video":2,"special_name":"\u5e94\u7528\u5316\u5b66","special_type":"1","type_name":"\u672c\u79d1","level3_name":"\u5316\u5b66\u7c7b","level3_code":"53","level2_name":"\u7406\u5b66","level2_id":"9","level2_code":"07","code":"0703"},{"id":"20568","school_id":"394","special_id":"182","nation_feature":"2","province_feature":"1","is_important":"2","limit_year":"\u56db\u5e74","year":"2022","level3_weight":"0","nation_first_class":"2","xueke_rank":"0","xueke_rank_score":"","ruanke_rank":"9999","ruanke_level":"","is_video":2,"special_name":"\u6c34\u5229\u6c34\u7535\u5de5\u7a0b","special_type":"1","type_name":"\u672c\u79d1","level3_name":"\u6c34\u5229\u7c7b","level3_code":"73","level2_name":"\u5de5\u5b66","level2_id":"10","level2_code":"08","code":"0811"},{"id":"20570","school_id":"394","special_id":"185","nation_feature":"2","province_feature":"1","is_important":"2","limit_year":"\u56db\u5e74","year":"2022","level3_weight":"0","nation_first_class":"2","xueke_rank":"0","xueke_rank_score":"","ruanke_rank":"77","ruanke_level":"B","is_video":1,"special_name":"\u6d4b\u7ed8\u5de5\u7a0b","special_type":"1","type_name":"\u672c\u79d1","level3_name":"\u6d4b\u7ed8\u7c7b","level3_code":"74","level2_name":"\u5de5\u5b66","level2_id":"10","level2_code":"08","code":"0812"},{"id":"20572","school_id":"394","special_id":"232","nation_feature":"2","province_feature":"2","is_important":"2","limit_year":"\u56db\u5e74","year":"2022","level3_weight":"0","nation_first_class":"2","xueke_rank":"0","xueke_rank_score":"","ruanke_rank":"9999","ruanke_level":"","is_video":1,"special_name":"\u73af\u5883\u5de5\u7a0b","special_type":"1","type_name":"\u672c\u79d1","level3_name":"\u73af\u5883\u79d1\u5b66\u4e0e\u5de5\u7a0b\u7c7b","level3_code":"87","level2_name":"\u5de5\u5b66","level2_id":"10","level2_code":"08","code":"0825"},{"id":"20604","school_id":"394","special_id":"180","nation_feature":"2","province_feature":"2","is_important":"2","limit_year":"\u56db\u5e74","year":"2022","level3_weight":"0","nation_first_class":"2","xueke_rank":"0","xueke_rank_score":"","ruanke_rank":"9999","ruanke_level":"","is_video":2,"special_name":"\u7ed9\u6392\u6c34\u79d1\u5b66\u4e0e\u5de5\u7a0b","special_type":"1","type_name":"\u672c\u79d1","level3_name":"\u571f\u6728\u7c7b","level3_code":"72","level2_name":"\u5de5\u5b66","level2_id":"10","level2_code":"08","code":"0810"},{"id":"20603","school_id":"394","special_id":"300","nation_feature":"2","province_feature":"2","is_important":"2","limit_year":"\u56db\u5e74","year":"2022","level3_weight":"0","nation_first_class":"2","xueke_rank":"0","xueke_rank_score":"","ruanke_rank":"324","ruanke_level":"B","is_video":2,"special_name":"\u8d22\u52a1\u7ba1\u7406","special_type":"1","type_name":"\u672c\u79d1","level3_name":"\u5de5\u5546\u7ba1\u7406\u7c7b","level3_code":"113","level2_name":"\u7ba1\u7406\u5b66","level2_id":"13","level2_code":"12","code":"1202"},{"id":"20598","school_id":"394","special_id":"173","nation_feature":"2","province_feature":"2","is_important":"2","limit_year":"\u56db\u5e74","year":"2022","level3_weight":"0","nation_first_class":"2","xueke_rank":"0","xueke_rank_score":"","ruanke_rank":"273","ruanke_level":"B","is_video":2,"special_name":"\u8f6f\u4ef6\u5de5\u7a0b","special_type":"1","type_name":"\u672c\u79d1","level3_name":"\u8ba1\u7b97\u673a\u7c7b","level3_code":"71","level2_name":"\u5de5\u5b66","level2_id":"10","level2_code":"08","code":"0809"},{"id":"20597","school_id":"394","special_id":"191","nation_feature":"2","province_feature":"1","is_important":"2","limit_year":"\u56db\u5e74","year":"2022","level3_weight":"0","nation_first_class":"2","xueke_rank":"0","xueke_rank_score":"","ruanke_rank":"9999","ruanke_level":"","is_video":2,"special_name":"\u8d44\u6e90\u52d8\u67e5\u5de5\u7a0b","special_type":"1","type_name":"\u672c\u79d1","level3_name":"\u5730\u8d28\u7c7b","level3_code":"76","level2_name":"\u5de5\u5b66","level2_id":"10","level2_code":"08","code":"0814"},{"id":"20580","school_id":"394","special_id":"45","nation_feature":"2","province_feature":"2","is_important":"2","limit_year":"\u56db\u5e74","year":"2022","level3_weight":"0","nation_first_class":"2","xueke_rank":"0","xueke_rank_score":"","ruanke_rank":"9999","ruanke_level":"","is_video":2,"special_name":"\u82f1\u8bed","special_type":"1","type_name":"\u672c\u79d1","level3_name":"\u5916\u56fd\u8bed\u8a00\u6587\u5b66\u7c7b","level3_code":"48","level2_name":"\u6587\u5b66","level2_id":"7","level2_code":"05","code":"0502"},{"id":"20579","school_id":"394","special_id":"298","nation_feature":"2","province_feature":"2","is_important":"2","limit_year":"\u56db\u5e74","year":"2022","level3_weight":"0","nation_first_class":"2","xueke_rank":"0","xueke_rank_score":"","ruanke_rank":"9999","ruanke_level":"","is_video":2,"special_name":"\u5e02\u573a\u8425\u9500","special_type":"1","type_name":"\u672c\u79d1","level3_name":"\u5de5\u5546\u7ba1\u7406\u7c7b","level3_code":"113","level2_name":"\u7ba1\u7406\u5b66","level2_id":"13","level2_code":"12","code":"1202"},{"id":"20576","school_id":"394","special_id":"297","nation_feature":"2","province_feature":"2","is_important":"2","limit_year":"\u56db\u5e74","year":"2022","level3_weight":"0","nation_first_class":"2","xueke_rank":"0","xueke_rank_score":"","ruanke_rank":"9999","ruanke_level":"","is_video":2,"special_name":"\u5de5\u5546\u7ba1\u7406","special_type":"1","type_name":"\u672c\u79d1","level3_name":"\u5de5\u5546\u7ba1\u7406\u7c7b","level3_code":"113","level2_name":"\u7ba1\u7406\u5b66","level2_id":"13","level2_code":"12","code":"1202"},{"id":"20575","school_id":"394","special_id":"296","nation_feature":"2","province_feature":"1","is_important":"2","limit_year":"\u56db\u5e74","year":"2022","level3_weight":"0","nation_first_class":"2","xueke_rank":"0","xueke_rank_score":"","ruanke_rank":"62","ruanke_level":"B","is_video":2,"special_name":"\u5de5\u7a0b\u9020\u4ef7","special_type":"1","type_name":"\u672c\u79d1","level3_name":"\u7ba1\u7406\u79d1\u5b66\u4e0e\u5de5\u7a0b\u7c7b","level3_code":"112","level2_name":"\u7ba1\u7406\u5b66","level2_id":"13","level2_code":"12","code":"1201"},{"id":"20574","school_id":"394","special_id":"294","nation_feature":"2","province_feature":"2","is_important":"2","limit_year":"\u56db\u5e74","year":"2022","level3_weight":"0","nation_first_class":"2","xueke_rank":"0","xueke_rank_score":"","ruanke_rank":"9999","ruanke_level":"","is_video":1,"special_name":"\u5de5\u7a0b\u7ba1\u7406","special_type":"1","type_name":"\u672c\u79d1","level3_name":"\u7ba1\u7406\u79d1\u5b66\u4e0e\u5de5\u7a0b\u7c7b","level3_code":"112","level2_name":"\u7ba1\u7406\u5b66","level2_id":"13","level2_code":"12","code":"1201"},{"id":"20553","school_id":"394","special_id":"163","nation_feature":"2","province_feature":"1","is_important":"2","limit_year":"\u56db\u5e74","year":"2022","level3_weight":"0","nation_first_class":"2","xueke_rank":"0","xueke_rank_score":"","ruanke_rank":"9999","ruanke_level":"","is_video":1,"special_name":"\u80fd\u6e90\u4e0e\u52a8\u529b\u5de5\u7a0b","special_type":"1","type_name":"\u672c\u79d1","level3_name":"\u80fd\u6e90\u52a8\u529b\u7c7b","level3_code":"67","level2_name":"\u5de5\u5b66","level2_id":"10","level2_code":"08","code":"0805"},{"id":"20547","school_id":"394","special_id":"176","nation_feature":"2","province_feature":"2","is_important":"2","limit_year":"\u56db\u5e74","year":"2022","level3_weight":"0","nation_first_class":"2","xueke_rank":"0","xueke_rank_score":"","ruanke_rank":"270","ruanke_level":"B","is_video":2,"special_name":"\u7269\u8054\u7f51\u5de5\u7a0b","special_type":"1","type_name":"\u672c\u79d1","level3_name":"\u8ba1\u7b97\u673a\u7c7b","level3_code":"71","level2_name":"\u5de5\u5b66","level2_id":"10","level2_code":"08","code":"0809"},{"id":"20595","school_id":"394","special_id":"1152","nation_feature":"2","province_feature":"2","is_important":"2","limit_year":"\u56db\u5e74","year":"2022","level3_weight":"0","nation_first_class":"2","xueke_rank":"0","xueke_rank_score":"","ruanke_rank":"9999","ruanke_level":"","is_video":2,"special_name":"\u65b0\u80fd\u6e90\u79d1\u5b66\u4e0e\u5de5\u7a0b","special_type":"1","type_name":"\u672c\u79d1","level3_name":"\u80fd\u6e90\u52a8\u529b\u7c7b","level3_code":"67","level2_name":"\u5de5\u5b66","level2_id":"10","level2_code":"08","code":"0805"},{"id":"20594","school_id":"394","special_id":"179","nation_feature":"2","province_feature":"2","is_important":"2","limit_year":"\u56db\u5e74","year":"2022","level3_weight":"0","nation_first_class":"2","xueke_rank":"0","xueke_rank_score":"","ruanke_rank":"9999","ruanke_level":"","is_video":1,"special_name":"\u5efa\u7b51\u73af\u5883\u4e0e\u80fd\u6e90\u5e94\u7528\u5de5\u7a0b","special_type":"1","type_name":"\u672c\u79d1","level3_name":"\u571f\u6728\u7c7b","level3_code":"72","level2_name":"\u5de5\u5b66","level2_id":"10","level2_code":"08","code":"0810"},{"id":"20565","school_id":"394","special_id":"242","nation_feature":"2","province_feature":"2","is_important":"2","limit_year":"\u56db\u5e74","year":"2022","level3_weight":"0","nation_first_class":"2","xueke_rank":"0","xueke_rank_score":"","ruanke_rank":"9999","ruanke_level":"","is_video":2,"special_name":"\u57ce\u4e61\u89c4\u5212","special_type":"1","type_name":"\u672c\u79d1","level3_name":"\u5efa\u7b51\u7c7b","level3_code":"90","level2_name":"\u5de5\u5b66","level2_id":"10","level2_code":"08","code":"0828"},{"id":"20582","school_id":"394","special_id":"349","nation_feature":"2","province_feature":"2","is_important":"2","limit_year":"\u56db\u5e74","year":"2022","level3_weight":"0","nation_first_class":"2","xueke_rank":"0","xueke_rank_score":"","ruanke_rank":"9999","ruanke_level":"","is_video":2,"special_name":"\u670d\u88c5\u4e0e\u670d\u9970\u8bbe\u8ba1","special_type":"1","type_name":"\u672c\u79d1","level3_name":"\u8bbe\u8ba1\u5b66\u7c7b","level3_code":"125","level2_name":"\u827a\u672f\u5b66","level2_id":"14","level2_code":"13","code":"1305"},{"id":"20583","school_id":"394","special_id":"348","nation_feature":"2","province_feature":"2","is_important":"2","limit_year":"\u56db\u5e74","year":"2022","level3_weight":"0","nation_first_class":"2","xueke_rank":"0","xueke_rank_score":"","ruanke_rank":"9999","ruanke_level":"","is_video":2,"special_name":"\u4ea7\u54c1\u8bbe\u8ba1","special_type":"1","type_name":"\u672c\u79d1","level3_name":"\u8bbe\u8ba1\u5b66\u7c7b","level3_code":"125","level2_name":"\u827a\u672f\u5b66","level2_id":"14","level2_code":"13","code":"1305"},{"id":"20584","school_id":"394","special_id":"347","nation_feature":"2","province_feature":"2","is_important":"2","limit_year":"\u56db\u5e74","year":"2022","level3_weight":"0","nation_first_class":"2","xueke_rank":"0","xueke_rank_score":"","ruanke_rank":"388","ruanke_level":"B","is_video":2,"special_name":"\u73af\u5883\u8bbe\u8ba1","special_type":"1","type_name":"\u672c\u79d1","level3_name":"\u8bbe\u8ba1\u5b66\u7c7b","level3_code":"125","level2_name":"\u827a\u672f\u5b66","level2_id":"14","level2_code":"13","code":"1305"},{"id":"20585","school_id":"394","special_id":"350","nation_feature":"2","province_feature":"2","is_important":"2","limit_year":"\u56db\u5e74","year":"2022","level3_weight":"0","nation_first_class":"2","xueke_rank":"0","xueke_rank_score":"","ruanke_rank":"9999","ruanke_level":"","is_video":2,"special_name":"\u516c\u5171\u827a\u672f","special_type":"1","type_name":"\u672c\u79d1","level3_name":"\u8bbe\u8ba1\u5b66\u7c7b","level3_code":"125","level2_name":"\u827a\u672f\u5b66","level2_id":"14","level2_code":"13","code":"1305"},{"id":"20607","school_id":"394","special_id":"233","nation_feature":"2","province_feature":"2","is_important":"2","limit_year":"\u56db\u5e74","year":"2022","level3_weight":"0","nation_first_class":"2","xueke_rank":"0","xueke_rank_score":"","ruanke_rank":"9999","ruanke_level":"","is_video":2,"special_name":"\u73af\u5883\u79d1\u5b66","special_type":"1","type_name":"\u672c\u79d1","level3_name":"\u73af\u5883\u79d1\u5b66\u4e0e\u5de5\u7a0b\u7c7b","level3_code":"87","level2_name":"\u5de5\u5b66","level2_id":"10","level2_code":"08","code":"0825"},{"id":"20608","school_id":"394","special_id":"244","nation_feature":"2","province_feature":"2","is_important":"2","limit_year":"\u56db\u5e74","year":"2022","level3_weight":"0","nation_first_class":"2","xueke_rank":"0","xueke_rank_score":"","ruanke_rank":"9999","ruanke_level":"","is_video":2,"special_name":"\u5b89\u5168\u5de5\u7a0b","special_type":"1","type_name":"\u672c\u79d1","level3_name":"\u5b89\u5168\u79d1\u5b66\u4e0e\u5de5\u7a0b\u7c7b","level3_code":"91","level2_name":"\u5de5\u5b66","level2_id":"10","level2_code":"08","code":"0829"},{"id":"20586","school_id":"394","special_id":"1148","nation_feature":"2","province_feature":"2","is_important":"2","limit_year":"\u56db\u5e74","year":"2022","level3_weight":"0","nation_first_class":"2","xueke_rank":"0","xueke_rank_score":"","ruanke_rank":"9999","ruanke_level":"","is_video":2,"special_name":"\u710a\u63a5\u6280\u672f\u4e0e\u5de5\u7a0b","special_type":"1","type_name":"\u672c\u79d1","level3_name":"\u6750\u6599\u7c7b","level3_code":"66","level2_name":"\u5de5\u5b66","level2_id":"10","level2_code":"08","code":"0804"},{"id":"20587","school_id":"394","special_id":"153","nation_feature":"2","province_feature":"2","is_important":"2","limit_year":"\u56db\u5e74","year":"2022","level3_weight":"0","nation_first_class":"2","xueke_rank":"0","xueke_rank_score":"","ruanke_rank":"74","ruanke_level":"B","is_video":1,"special_name":"\u6c7d\u8f66\u670d\u52a1\u5de5\u7a0b","special_type":"1","type_name":"\u672c\u79d1","level3_name":"\u673a\u68b0\u7c7b","level3_code":"64","level2_name":"\u5de5\u5b66","level2_id":"10","level2_code":"08","code":"0802"},{"id":"20577","school_id":"394","special_id":"295","nation_feature":"2","province_feature":"2","is_important":"2","limit_year":"\u56db\u5e74","year":"2022","level3_weight":"0","nation_first_class":"2","xueke_rank":"0","xueke_rank_score":"","ruanke_rank":"9999","ruanke_level":"","is_video":2,"special_name":"\u623f\u5730\u4ea7\u5f00\u53d1\u4e0e\u7ba1\u7406","special_type":"1","type_name":"\u672c\u79d1","level3_name":"\u7ba1\u7406\u79d1\u5b66\u4e0e\u5de5\u7a0b\u7c7b","level3_code":"112","level2_name":"\u7ba1\u7406\u5b66","level2_id":"13","level2_code":"12","code":"1201"},{"id":"20591","school_id":"394","special_id":"1172","nation_feature":"2","province_feature":"2","is_important":"2","limit_year":"\u56db\u5e74","year":"2022","level3_weight":"0","nation_first_class":"2","xueke_rank":"0","xueke_rank_score":"","ruanke_rank":"9999","ruanke_level":"","is_video":2,"special_name":"\u9053\u8def\u6865\u6881\u4e0e\u6e21\u6cb3\u5de5\u7a0b","special_type":"1","type_name":"\u672c\u79d1","level3_name":"\u571f\u6728\u7c7b","level3_code":"72","level2_name":"\u5de5\u5b66","level2_id":"10","level2_code":"08","code":"0810"},{"id":"20592","school_id":"394","special_id":"1171","nation_feature":"2","province_feature":"2","is_important":"2","limit_year":"\u56db\u5e74","year":"2022","level3_weight":"0","nation_first_class":"2","xueke_rank":"0","xueke_rank_score":"","ruanke_rank":"9999","ruanke_level":"","is_video":2,"special_name":"\u57ce\u5e02\u5730\u4e0b\u7a7a\u95f4\u5de5\u7a0b","special_type":"1","type_name":"\u672c\u79d1","level3_name":"\u571f\u6728\u7c7b","level3_code":"72","level2_name":"\u5de5\u5b66","level2_id":"10","level2_code":"08","code":"0810"},{"id":"20558","school_id":"394","special_id":"1154","nation_feature":"2","province_feature":"2","is_important":"2","limit_year":"\u56db\u5e74","year":"2022","level3_weight":"0","nation_first_class":"2","xueke_rank":"0","xueke_rank_score":"","ruanke_rank":"9999","ruanke_level":"","is_video":2,"special_name":"\u667a\u80fd\u7535\u7f51\u4fe1\u606f\u5de5\u7a0b","special_type":"1","type_name":"\u672c\u79d1","level3_name":"\u7535\u6c14\u7c7b","level3_code":"68","level2_name":"\u5de5\u5b66","level2_id":"10","level2_code":"08","code":"0806"},{"id":"1035557","school_id":"394","special_id":"147","nation_feature":"1","province_feature":"2","is_important":"2","limit_year":"\u56db\u5e74","year":"2022","level3_weight":"0","nation_first_class":"2","xueke_rank":"0","xueke_rank_score":"","ruanke_rank":"245","ruanke_level":"B","is_video":2,"special_name":"\u673a\u68b0\u8bbe\u8ba1\u5236\u9020\u53ca\u5176\u81ea\u52a8\u5316(\u4e2d\u5916\u5408\u4f5c\u529e\u5b66)","special_type":"1","type_name":"\u672c\u79d1","level3_name":"\u673a\u68b0\u7c7b","level3_code":"64","level2_name":"\u5de5\u5b66","level2_id":"10","level2_code":"08","code":"0802"},{"id":"1035558","school_id":"394","special_id":"163","nation_feature":"2","province_feature":"2","is_important":"2","limit_year":"\u56db\u5e74","year":"2022","level3_weight":"0","nation_first_class":"2","xueke_rank":"0","xueke_rank_score":"","ruanke_rank":"9999","ruanke_level":"","is_video":1,"special_name":"\u80fd\u6e90\u4e0e\u52a8\u529b\u5de5\u7a0b(\u4e2d\u5916\u5408\u4f5c\u529e\u5b66)","special_type":"1","type_name":"\u672c\u79d1","level3_name":"\u80fd\u6e90\u52a8\u529b\u7c7b","level3_code":"67","level2_name":"\u5de5\u5b66","level2_id":"10","level2_code":"08","code":"0805"},{"id":"1035559","school_id":"394","special_id":"178","nation_feature":"2","province_feature":"2","is_important":"2","limit_year":"\u56db\u5e74","year":"2022","level3_weight":"0","nation_first_class":"2","xueke_rank":"0","xueke_rank_score":"","ruanke_rank":"215","ruanke_level":"B","is_video":2,"special_name":"\u571f\u6728\u5de5\u7a0b(\u4e2d\u5916\u5408\u4f5c\u529e\u5b66)","special_type":"1","type_name":"\u672c\u79d1","level3_name":"\u571f\u6728\u7c7b","level3_code":"72","level2_name":"\u5de5\u5b66","level2_id":"10","level2_code":"08","code":"0810"},{"id":"1130027","school_id":"394","special_id":"8393","nation_feature":"2","province_feature":"2","is_important":"2","limit_year":"\u56db\u5e74","year":"2022","level3_weight":"0","nation_first_class":"2","xueke_rank":"0","xueke_rank_score":"","ruanke_rank":"9999","ruanke_level":"","is_video":2,"special_name":"\u667a\u80fd\u5efa\u9020","special_type":"1","type_name":"\u672c\u79d1","level3_name":"\u571f\u6728\u7c7b","level3_code":"72","level2_name":"\u5de5\u5b66","level2_id":"10","level2_code":"08","code":"0810"},{"id":"2012215","school_id":"394","special_id":"1149","nation_feature":"2","province_feature":"2","is_important":"2","limit_year":"\u56db\u5e74","year":"2022","level3_weight":"0","nation_first_class":"2","xueke_rank":"0","xueke_rank_score":"","ruanke_rank":"9999","ruanke_level":"","is_video":2,"special_name":"\u529f\u80fd\u6750\u6599","special_type":"1","type_name":"\u672c\u79d1","level3_name":"\u6750\u6599\u7c7b","level3_code":"66","level2_name":"\u5de5\u5b66","level2_id":"10","level2_code":"08","code":"0804"},{"id":"1582484","school_id":"394","special_id":"8410","nation_feature":"2","province_feature":"2","is_important":"2","limit_year":"\u56db\u5e74","year":"2022","level3_weight":"0","nation_first_class":"2","xueke_rank":"0","xueke_rank_score":"","ruanke_rank":"9999","ruanke_level":"","is_video":1,"special_name":"\u5e94\u6025\u6280\u672f\u4e0e\u7ba1\u7406","special_type":"1","type_name":"\u672c\u79d1","level3_name":"\u5b89\u5168\u79d1\u5b66\u4e0e\u5de5\u7a0b\u7c7b","level3_code":"91","level2_name":"\u5de5\u5b66","level2_id":"10","level2_code":"08","code":"0829"},{"id":"169371","school_id":"394","special_id":"1282","nation_feature":"2","province_feature":"2","is_important":"2","limit_year":"\u56db\u5e74","year":"2022","level3_weight":"0","nation_first_class":"2","xueke_rank":"0","xueke_rank_score":"","ruanke_rank":"9999","ruanke_level":"","is_video":2,"special_name":"\u673a\u5668\u4eba\u5de5\u7a0b","special_type":"1","type_name":"\u672c\u79d1","level3_name":"\u81ea\u52a8\u5316\u7c7b","level3_code":"70","level2_name":"\u5de5\u5b66","level2_id":"10","level2_code":"08","code":"0808"},{"id":"169372","school_id":"394","special_id":"1283","nation_feature":"2","province_feature":"2","is_important":"2","limit_year":"\u56db\u5e74","year":"2022","level3_weight":"0","nation_first_class":"2","xueke_rank":"0","xueke_rank_score":"","ruanke_rank":"9999","ruanke_level":"","is_video":2,"special_name":"\u6570\u636e\u79d1\u5b66\u4e0e\u5927\u6570\u636e\u6280\u672f","special_type":"1","type_name":"\u672c\u79d1","level3_name":"\u8ba1\u7b97\u673a\u7c7b","level3_code":"71","level2_name":"\u5de5\u5b66","level2_id":"10","level2_code":"08","code":"0809"},{"id":"2012332","school_id":"394","special_id":"9338","nation_feature":"2","province_feature":"2","is_important":"2","limit_year":"\u56db\u5e74","year":"2022","level3_weight":"0","nation_first_class":"2","xueke_rank":"0","xueke_rank_score":"","ruanke_rank":"9999","ruanke_level":"","is_video":2,"special_name":"\u667a\u80fd\u8fd0\u8f93\u5de5\u7a0b","special_type":"1","type_name":"\u672c\u79d1","level3_name":"\u4ea4\u901a\u8fd0\u8f93\u7c7b","level3_code":"80","level2_name":"\u5de5\u5b66","level2_id":"10","level2_code":"08","code":"0818"},{"id":"1585070","school_id":"394","special_id":"8380","nation_feature":"2","province_feature":"2","is_important":"2","limit_year":"\u56db\u5e74","year":"2022","level3_weight":"0","nation_first_class":"2","xueke_rank":"0","xueke_rank_score":"","ruanke_rank":"9999","ruanke_level":"","is_video":2,"special_name":"\u667a\u80fd\u8f66\u8f86\u5de5\u7a0b","special_type":"1","type_name":"\u672c\u79d1","level3_name":"\u673a\u68b0\u7c7b","level3_code":"64","level2_name":"\u5de5\u5b66","level2_id":"10","level2_code":"08","code":"0802"},{"id":"2011901","school_id":"394","special_id":"8687","nation_feature":"2","province_feature":"2","is_important":"2","limit_year":"\u56db\u5e74","year":"2022","level3_weight":"0","nation_first_class":"2","xueke_rank":"0","xueke_rank_score":"","ruanke_rank":"9999","ruanke_level":"","is_video":2,"special_name":"\u5e94\u6025\u7ba1\u7406","special_type":"1","type_name":"\u672c\u79d1","level3_name":"\u7ba1\u7406\u79d1\u5b66\u4e0e\u5de5\u7a0b\u7c7b","level3_code":"112","level2_name":"\u7ba1\u7406\u5b66","level2_id":"13","level2_code":"12","code":"1201"}],"2":[{"id":"20609","school_id":"394","special_id":"784","nation_feature":"2","province_feature":"2","is_important":"2","limit_year":"\u4e09\u5e74","year":"2022","level3_weight":"0","nation_first_class":"2","xueke_rank":"0","xueke_rank_score":"","ruanke_rank":"9999","ruanke_level":"","is_video":2,"special_name":"\u8ba1\u7b97\u673a\u7f51\u7edc\u6280\u672f","special_type":"2","type_name":"\u4e13\u79d1\uff08\u9ad8\u804c\uff09","level3_name":"\u8ba1\u7b97\u673a\u7c7b","level3_code":"183","level2_name":"\u7535\u5b50\u4e0e\u4fe1\u606f\u5927\u7c7b","level2_id":"25","level2_code":"51","code":"5102"},{"id":"20611","school_id":"394","special_id":"886","nation_feature":"2","province_feature":"2","is_important":"2","limit_year":"\u4e09\u5e74","year":"2022","level3_weight":"0","nation_first_class":"2","xueke_rank":"0","xueke_rank_score":"","ruanke_rank":"9999","ruanke_level":"","is_video":2,"special_name":"\u7535\u5b50\u5546\u52a1","special_type":"2","type_name":"\u4e13\u79d1\uff08\u9ad8\u804c\uff09","level3_name":"\u7535\u5b50\u5546\u52a1\u7c7b","level3_code":"200","level2_name":"\u8d22\u7ecf\u5546\u8d38\u5927\u7c7b","level2_id":"27","level2_code":"53","code":"5307"},{"id":"20569","school_id":"394","special_id":"556","nation_feature":"2","province_feature":"2","is_important":"2","limit_year":"\u4e09\u5e74","year":"2022","level3_weight":"0","nation_first_class":"2","xueke_rank":"0","xueke_rank_score":"","ruanke_rank":"9999","ruanke_level":"","is_video":2,"special_name":"\u6c34\u5229\u6c34\u7535\u5efa\u7b51\u5de5\u7a0b","special_type":"2","type_name":"\u4e13\u79d1\uff08\u9ad8\u804c\uff09","level3_name":"\u6c34\u5229\u5de5\u7a0b\u4e0e\u7ba1\u7406\u7c7b","level3_code":"154","level2_name":"\u6c34\u5229\u5927\u7c7b","level2_id":"19","level2_code":"45","code":"4502"},{"id":"20560","school_id":"394","special_id":"469","nation_feature":"2","province_feature":"2","is_important":"2","limit_year":"\u4e09\u5e74","year":"2022","level3_weight":"0","nation_first_class":"2","xueke_rank":"0","xueke_rank_score":"","ruanke_rank":"9999","ruanke_level":"","is_video":2,"special_name":"\u53d1\u7535\u5382\u53ca\u7535\u529b\u7cfb\u7edf","special_type":"2","type_name":"\u4e13\u79d1\uff08\u9ad8\u804c\uff09","level3_name":"\u7535\u529b\u6280\u672f\u7c7b","level3_code":"139","level2_name":"\u80fd\u6e90\u52a8\u529b\u4e0e\u6750\u6599\u5927\u7c7b","level2_id":"17","level2_code":"43","code":"4301"},{"id":"1790246","school_id":"394","special_id":"8982","nation_feature":"2","province_feature":"2","is_important":"2","limit_year":"\u4e09\u5e74","year":"2022","level3_weight":"0","nation_first_class":"2","xueke_rank":"0","xueke_rank_score":"","ruanke_rank":"9999","ruanke_level":"","is_video":2,"special_name":"\u6c34\u7535\u7ad9\u8bbe\u5907\u5b89\u88c5\u4e0e\u7ba1\u7406","special_type":"2","type_name":"\u4e13\u79d1\uff08\u9ad8\u804c\uff09","level3_name":"\u6c34\u5229\u6c34\u7535\u8bbe\u5907\u7c7b","level3_code":"155","level2_name":"\u6c34\u5229\u5927\u7c7b","level2_id":"19","level2_code":"45","code":"4503"},{"id":"1790247","school_id":"394","special_id":"8990","nation_feature":"2","province_feature":"2","is_important":"2","limit_year":"\u4e09\u5e74","year":"2022","level3_weight":"0","nation_first_class":"2","xueke_rank":"0","xueke_rank_score":"","ruanke_rank":"9999","ruanke_level":"","is_video":2,"special_name":"\u667a\u80fd\u710a\u63a5\u6280\u672f","special_type":"2","type_name":"\u4e13\u79d1\uff08\u9ad8\u804c\uff09","level3_name":"\u673a\u68b0\u8bbe\u8ba1\u5236\u9020\u7c7b","level3_code":"157","level2_name":"\u88c5\u5907\u5236\u9020\u5927\u7c7b","level2_id":"20","level2_code":"46","code":"4601"},{"id":"1790248","school_id":"394","special_id":"9161","nation_feature":"2","province_feature":"2","is_important":"2","limit_year":"\u4e09\u5e74","year":"2022","level3_weight":"0","nation_first_class":"2","xueke_rank":"0","xueke_rank_score":"","ruanke_rank":"9999","ruanke_level":"","is_video":2,"special_name":"\u673a\u68b0\u5236\u9020\u53ca\u81ea\u52a8\u5316","special_type":"2","type_name":"\u4e13\u79d1\uff08\u9ad8\u804c\uff09","level3_name":"\u673a\u68b0\u8bbe\u8ba1\u5236\u9020\u7c7b","level3_code":"157","level2_name":"\u88c5\u5907\u5236\u9020\u5927\u7c7b","level2_id":"20","level2_code":"46","code":"4601"},{"id":"1790249","school_id":"394","special_id":"9176","nation_feature":"2","province_feature":"2","is_important":"2","limit_year":"\u4e09\u5e74","year":"2022","level3_weight":"0","nation_first_class":"2","xueke_rank":"0","xueke_rank_score":"","ruanke_rank":"9999","ruanke_level":"","is_video":2,"special_name":"\u6570\u5b57\u5a92\u4f53\u6280\u672f","special_type":"2","type_name":"\u4e13\u79d1\uff08\u9ad8\u804c\uff09","level3_name":"\u8ba1\u7b97\u673a\u7c7b","level3_code":"183","level2_name":"\u7535\u5b50\u4e0e\u4fe1\u606f\u5927\u7c7b","level2_id":"25","level2_code":"51","code":"5102"}],"3":"","4":[]},"special":[{"level3_weight":"0","code":"0502","name":"\u5916\u56fd\u8bed\u8a00\u6587\u5b66\u7c7b(\u672c)","special":[{"id":"20580","school_id":"394","special_id":"45","nation_feature":"2","province_feature":"2","is_important":"2","limit_year":"\u56db\u5e74","year":"2022","level3_weight":"0","nation_first_class":"2","xueke_rank":"0","xueke_rank_score":"","ruanke_rank":"9999","ruanke_level":"","is_video":2,"special_name":"\u82f1\u8bed","special_type":"1","type_name":"\u672c\u79d1","level3_name":"\u5916\u56fd\u8bed\u8a00\u6587\u5b66\u7c7b","level3_code":"48","level2_name":"\u6587\u5b66","level2_id":"7","level2_code":"05","code":"0502"}]},{"level3_weight":"0","code":"0703","name":"\u5316\u5b66\u7c7b(\u672c)","special":[{"id":"20550","school_id":"394","special_id":"122","nation_feature":"2","province_feature":"2","is_important":"2","limit_year":"\u56db\u5e74","year":"2022","level3_weight":"0","nation_first_class":"2","xueke_rank":"0","xueke_rank_score":"","ruanke_rank":"9999","ruanke_level":"","is_video":2,"special_name":"\u5e94\u7528\u5316\u5b66","special_type":"1","type_name":"\u672c\u79d1","level3_name":"\u5316\u5b66\u7c7b","level3_code":"53","level2_name":"\u7406\u5b66","level2_id":"9","level2_code":"07","code":"0703"}]},{"level3_weight":"0","code":"0802","name":"\u673a\u68b0\u7c7b(\u672c)","special":[{"id":"20552","school_id":"394","special_id":"147","nation_feature":"1","province_feature":"1","is_important":"2","limit_year":"\u56db\u5e74","year":"2022","level3_weight":"0","nation_first_class":"2","xueke_rank":"0","xueke_rank_score":"","ruanke_rank":"245","ruanke_level":"B","is_video":2,"special_name":"\u673a\u68b0\u8bbe\u8ba1\u5236\u9020\u53ca\u5176\u81ea\u52a8\u5316","special_type":"1","type_name":"\u672c\u79d1","level3_name":"\u673a\u68b0\u7c7b","level3_code":"64","level2_name":"\u5de5\u5b66","level2_id":"10","level2_code":"08","code":"0802"},{"id":"20555","school_id":"394","special_id":"148","nation_feature":"2","province_feature":"2","is_important":"2","limit_year":"\u56db\u5e74","year":"2022","level3_weight":"0","nation_first_class":"2","xueke_rank":"0","xueke_rank_score":"","ruanke_rank":"9999","ruanke_level":"","is_video":2,"special_name":"\u6750\u6599\u6210\u578b\u53ca\u63a7\u5236\u5de5\u7a0b","special_type":"1","type_name":"\u672c\u79d1","level3_name":"\u673a\u68b0\u7c7b","level3_code":"64","level2_name":"\u5de5\u5b66","level2_id":"10","level2_code":"08","code":"0802"},{"id":"20587","school_id":"394","special_id":"153","nation_feature":"2","province_feature":"2","is_important":"2","limit_year":"\u56db\u5e74","year":"2022","level3_weight":"0","nation_first_class":"2","xueke_rank":"0","xueke_rank_score":"","ruanke_rank":"74","ruanke_level":"B","is_video":1,"special_name":"\u6c7d\u8f66\u670d\u52a1\u5de5\u7a0b","special_type":"1","type_name":"\u672c\u79d1","level3_name":"\u673a\u68b0\u7c7b","level3_code":"64","level2_name":"\u5de5\u5b66","level2_id":"10","level2_code":"08","code":"0802"},{"id":"1035557","school_id":"394","special_id":"147","nation_feature":"1","province_feature":"2","is_important":"2","limit_year":"\u56db\u5e74","year":"2022","level3_weight":"0","nation_first_class":"2","xueke_rank":"0","xueke_rank_score":"","ruanke_rank":"245","ruanke_level":"B","is_video":2,"special_name":"\u673a\u68b0\u8bbe\u8ba1\u5236\u9020\u53ca\u5176\u81ea\u52a8\u5316(\u4e2d\u5916\u5408\u4f5c\u529e\u5b66)","special_type":"1","type_name":"\u672c\u79d1","level3_name":"\u673a\u68b0\u7c7b","level3_code":"64","level2_name":"\u5de5\u5b66","level2_id":"10","level2_code":"08","code":"0802"},{"id":"1585070","school_id":"394","special_id":"8380","nation_feature":"2","province_feature":"2","is_important":"2","limit_year":"\u56db\u5e74","year":"2022","level3_weight":"0","nation_first_class":"2","xueke_rank":"0","xueke_rank_score":"","ruanke_rank":"9999","ruanke_level":"","is_video":2,"special_name":"\u667a\u80fd\u8f66\u8f86\u5de5\u7a0b","special_type":"1","type_name":"\u672c\u79d1","level3_name":"\u673a\u68b0\u7c7b","level3_code":"64","level2_name":"\u5de5\u5b66","level2_id":"10","level2_code":"08","code":"0802"}]},{"level3_weight":"0","code":"0804","name":"\u6750\u6599\u7c7b(\u672c)","special":[{"id":"20605","school_id":"394","special_id":"1147","nation_feature":"2","province_feature":"2","is_important":"2","limit_year":"\u56db\u5e74","year":"2022","level3_weight":"0","nation_first_class":"2","xueke_rank":"0","xueke_rank_score":"","ruanke_rank":"9999","ruanke_level":"","is_video":2,"special_name":"\u5b9d\u77f3\u53ca\u6750\u6599\u5de5\u827a\u5b66","special_type":"1","type_name":"\u672c\u79d1","level3_name":"\u6750\u6599\u7c7b","level3_code":"66","level2_name":"\u5de5\u5b66","level2_id":"10","level2_code":"08","code":"0804"},{"id":"20586","school_id":"394","special_id":"1148","nation_feature":"2","province_feature":"2","is_important":"2","limit_year":"\u56db\u5e74","year":"2022","level3_weight":"0","nation_first_class":"2","xueke_rank":"0","xueke_rank_score":"","ruanke_rank":"9999","ruanke_level":"","is_video":2,"special_name":"\u710a\u63a5\u6280\u672f\u4e0e\u5de5\u7a0b","special_type":"1","type_name":"\u672c\u79d1","level3_name":"\u6750\u6599\u7c7b","level3_code":"66","level2_name":"\u5de5\u5b66","level2_id":"10","level2_code":"08","code":"0804"},{"id":"2012215","school_id":"394","special_id":"1149","nation_feature":"2","province_feature":"2","is_important":"2","limit_year":"\u56db\u5e74","year":"2022","level3_weight":"0","nation_first_class":"2","xueke_rank":"0","xueke_rank_score":"","ruanke_rank":"9999","ruanke_level":"","is_video":2,"special_name":"\u529f\u80fd\u6750\u6599","special_type":"1","type_name":"\u672c\u79d1","level3_name":"\u6750\u6599\u7c7b","level3_code":"66","level2_name":"\u5de5\u5b66","level2_id":"10","level2_code":"08","code":"0804"}]},{"level3_weight":"0","code":"0805","name":"\u80fd\u6e90\u52a8\u529b\u7c7b(\u672c)","special":[{"id":"20553","school_id":"394","special_id":"163","nation_feature":"2","province_feature":"1","is_important":"2","limit_year":"\u56db\u5e74","year":"2022","level3_weight":"0","nation_first_class":"2","xueke_rank":"0","xueke_rank_score":"","ruanke_rank":"9999","ruanke_level":"","is_video":1,"special_name":"\u80fd\u6e90\u4e0e\u52a8\u529b\u5de5\u7a0b","special_type":"1","type_name":"\u672c\u79d1","level3_name":"\u80fd\u6e90\u52a8\u529b\u7c7b","level3_code":"67","level2_name":"\u5de5\u5b66","level2_id":"10","level2_code":"08","code":"0805"},{"id":"20595","school_id":"394","special_id":"1152","nation_feature":"2","province_feature":"2","is_important":"2","limit_year":"\u56db\u5e74","year":"2022","level3_weight":"0","nation_first_class":"2","xueke_rank":"0","xueke_rank_score":"","ruanke_rank":"9999","ruanke_level":"","is_video":2,"special_name":"\u65b0\u80fd\u6e90\u79d1\u5b66\u4e0e\u5de5\u7a0b","special_type":"1","type_name":"\u672c\u79d1","level3_name":"\u80fd\u6e90\u52a8\u529b\u7c7b","level3_code":"67","level2_name":"\u5de5\u5b66","level2_id":"10","level2_code":"08","code":"0805"},{"id":"1035558","school_id":"394","special_id":"163","nation_feature":"2","province_feature":"2","is_important":"2","limit_year":"\u56db\u5e74","year":"2022","level3_weight":"0","nation_first_class":"2","xueke_rank":"0","xueke_rank_score":"","ruanke_rank":"9999","ruanke_level":"","is_video":1,"special_name":"\u80fd\u6e90\u4e0e\u52a8\u529b\u5de5\u7a0b(\u4e2d\u5916\u5408\u4f5c\u529e\u5b66)","special_type":"1","type_name":"\u672c\u79d1","level3_name":"\u80fd\u6e90\u52a8\u529b\u7c7b","level3_code":"67","level2_name":"\u5de5\u5b66","level2_id":"10","level2_code":"08","code":"0805"}]},{"level3_weight":"0","code":"0806","name":"\u7535\u6c14\u7c7b(\u672c)","special":[{"id":"20557","school_id":"394","special_id":"164","nation_feature":"1","province_feature":"1","is_important":"2","limit_year":"\u56db\u5e74","year":"2022","level3_weight":"0","nation_first_class":"2","xueke_rank":"0","xueke_rank_score":"","ruanke_rank":"179","ruanke_level":"B","is_video":1,"special_name":"\u7535\u6c14\u5de5\u7a0b\u53ca\u5176\u81ea\u52a8\u5316","special_type":"1","type_name":"\u672c\u79d1","level3_name":"\u7535\u6c14\u7c7b","level3_code":"68","level2_name":"\u5de5\u5b66","level2_id":"10","level2_code":"08","code":"0806"},{"id":"20558","school_id":"394","special_id":"1154","nation_feature":"2","province_feature":"2","is_important":"2","limit_year":"\u56db\u5e74","year":"2022","level3_weight":"0","nation_first_class":"2","xueke_rank":"0","xueke_rank_score":"","ruanke_rank":"9999","ruanke_level":"","is_video":2,"special_name":"\u667a\u80fd\u7535\u7f51\u4fe1\u606f\u5de5\u7a0b","special_type":"1","type_name":"\u672c\u79d1","level3_name":"\u7535\u6c14\u7c7b","level3_code":"68","level2_name":"\u5de5\u5b66","level2_id":"10","level2_code":"08","code":"0806"}]},{"level3_weight":"0","code":"0807","name":"\u7535\u5b50\u4fe1\u606f\u7c7b(\u672c)","special":[{"id":"20561","school_id":"394","special_id":"165","nation_feature":"2","province_feature":"2","is_important":"2","limit_year":"\u56db\u5e74","year":"2022","level3_weight":"0","nation_first_class":"2","xueke_rank":"0","xueke_rank_score":"","ruanke_rank":"9999","ruanke_level":"","is_video":1,"special_name":"\u7535\u5b50\u4fe1\u606f\u5de5\u7a0b","special_type":"1","type_name":"\u672c\u79d1","level3_name":"\u7535\u5b50\u4fe1\u606f\u7c7b","level3_code":"69","level2_name":"\u5de5\u5b66","level2_id":"10","level2_code":"08","code":"0807"}]},{"level3_weight":"0","code":"0808","name":"\u81ea\u52a8\u5316\u7c7b(\u672c)","special":[{"id":"20559","school_id":"394","special_id":"171","nation_feature":"2","province_feature":"2","is_important":"2","limit_year":"\u56db\u5e74","year":"2022","level3_weight":"0","nation_first_class":"2","xueke_rank":"0","xueke_rank_score":"","ruanke_rank":"9999","ruanke_level":"","is_video":2,"special_name":"\u81ea\u52a8\u5316","special_type":"1","type_name":"\u672c\u79d1","level3_name":"\u81ea\u52a8\u5316\u7c7b","level3_code":"70","level2_name":"\u5de5\u5b66","level2_id":"10","level2_code":"08","code":"0808"},{"id":"169371","school_id":"394","special_id":"1282","nation_feature":"2","province_feature":"2","is_important":"2","limit_year":"\u56db\u5e74","year":"2022","level3_weight":"0","nation_first_class":"2","xueke_rank":"0","xueke_rank_score":"","ruanke_rank":"9999","ruanke_level":"","is_video":2,"special_name":"\u673a\u5668\u4eba\u5de5\u7a0b","special_type":"1","type_name":"\u672c\u79d1","level3_name":"\u81ea\u52a8\u5316\u7c7b","level3_code":"70","level2_name":"\u5de5\u5b66","level2_id":"10","level2_code":"08","code":"0808"}]},{"level3_weight":"0","code":"0809","name":"\u8ba1\u7b97\u673a\u7c7b(\u672c)","special":[{"id":"20556","school_id":"394","special_id":"172","nation_feature":"2","province_feature":"2","is_important":"2","limit_year":"\u56db\u5e74","year":"2022","level3_weight":"0","nation_first_class":"2","xueke_rank":"0","xueke_rank_score":"","ruanke_rank":"9999","ruanke_level":"","is_video":1,"special_name":"\u8ba1\u7b97\u673a\u79d1\u5b66\u4e0e\u6280\u672f","special_type":"1","type_name":"\u672c\u79d1","level3_name":"\u8ba1\u7b97\u673a\u7c7b","level3_code":"71","level2_name":"\u5de5\u5b66","level2_id":"10","level2_code":"08","code":"0809"},{"id":"20598","school_id":"394","special_id":"173","nation_feature":"2","province_feature":"2","is_important":"2","limit_year":"\u56db\u5e74","year":"2022","level3_weight":"0","nation_first_class":"2","xueke_rank":"0","xueke_rank_score":"","ruanke_rank":"273","ruanke_level":"B","is_video":2,"special_name":"\u8f6f\u4ef6\u5de5\u7a0b","special_type":"1","type_name":"\u672c\u79d1","level3_name":"\u8ba1\u7b97\u673a\u7c7b","level3_code":"71","level2_name":"\u5de5\u5b66","level2_id":"10","level2_code":"08","code":"0809"},{"id":"20547","school_id":"394","special_id":"176","nation_feature":"2","province_feature":"2","is_important":"2","limit_year":"\u56db\u5e74","year":"2022","level3_weight":"0","nation_first_class":"2","xueke_rank":"0","xueke_rank_score":"","ruanke_rank":"270","ruanke_level":"B","is_video":2,"special_name":"\u7269\u8054\u7f51\u5de5\u7a0b","special_type":"1","type_name":"\u672c\u79d1","level3_name":"\u8ba1\u7b97\u673a\u7c7b","level3_code":"71","level2_name":"\u5de5\u5b66","level2_id":"10","level2_code":"08","code":"0809"},{"id":"169372","school_id":"394","special_id":"1283","nation_feature":"2","province_feature":"2","is_important":"2","limit_year":"\u56db\u5e74","year":"2022","level3_weight":"0","nation_first_class":"2","xueke_rank":"0","xueke_rank_score":"","ruanke_rank":"9999","ruanke_level":"","is_video":2,"special_name":"\u6570\u636e\u79d1\u5b66\u4e0e\u5927\u6570\u636e\u6280\u672f","special_type":"1","type_name":"\u672c\u79d1","level3_name":"\u8ba1\u7b97\u673a\u7c7b","level3_code":"71","level2_name":"\u5de5\u5b66","level2_id":"10","level2_code":"08","code":"0809"}]},{"level3_weight":"0","code":"0810","name":"\u571f\u6728\u7c7b(\u672c)","special":[{"id":"20612","school_id":"394","special_id":"181","nation_feature":"2","province_feature":"2","is_important":"2","limit_year":"\u56db\u5e74","year":"2022","level3_weight":"0","nation_first_class":"2","xueke_rank":"0","xueke_rank_score":"","ruanke_rank":"42","ruanke_level":"B","is_video":2,"special_name":"\u5efa\u7b51\u7535\u6c14\u4e0e\u667a\u80fd\u5316","special_type":"1","type_name":"\u672c\u79d1","level3_name":"\u571f\u6728\u7c7b","level3_code":"72","level2_name":"\u5de5\u5b66","level2_id":"10","level2_code":"08","code":"0810"},{"id":"20563","school_id":"394","special_id":"178","nation_feature":"2","province_feature":"1","is_important":"2","limit_year":"\u56db\u5e74","year":"2022","level3_weight":"0","nation_first_class":"2","xueke_rank":"0","xueke_rank_score":"","ruanke_rank":"215","ruanke_level":"B","is_video":2,"special_name":"\u571f\u6728\u5de5\u7a0b","special_type":"1","type_name":"\u672c\u79d1","level3_name":"\u571f\u6728\u7c7b","level3_code":"72","level2_name":"\u5de5\u5b66","level2_id":"10","level2_code":"08","code":"0810"},{"id":"20604","school_id":"394","special_id":"180","nation_feature":"2","province_feature":"2","is_important":"2","limit_year":"\u56db\u5e74","year":"2022","level3_weight":"0","nation_first_class":"2","xueke_rank":"0","xueke_rank_score":"","ruanke_rank":"9999","ruanke_level":"","is_video":2,"special_name":"\u7ed9\u6392\u6c34\u79d1\u5b66\u4e0e\u5de5\u7a0b","special_type":"1","type_name":"\u672c\u79d1","level3_name":"\u571f\u6728\u7c7b","level3_code":"72","level2_name":"\u5de5\u5b66","level2_id":"10","level2_code":"08","code":"0810"},{"id":"20594","school_id":"394","special_id":"179","nation_feature":"2","province_feature":"2","is_important":"2","limit_year":"\u56db\u5e74","year":"2022","level3_weight":"0","nation_first_class":"2","xueke_rank":"0","xueke_rank_score":"","ruanke_rank":"9999","ruanke_level":"","is_video":1,"special_name":"\u5efa\u7b51\u73af\u5883\u4e0e\u80fd\u6e90\u5e94\u7528\u5de5\u7a0b","special_type":"1","type_name":"\u672c\u79d1","level3_name":"\u571f\u6728\u7c7b","level3_code":"72","level2_name":"\u5de5\u5b66","level2_id":"10","level2_code":"08","code":"0810"},{"id":"20591","school_id":"394","special_id":"1172","nation_feature":"2","province_feature":"2","is_important":"2","limit_year":"\u56db\u5e74","year":"2022","level3_weight":"0","nation_first_class":"2","xueke_rank":"0","xueke_rank_score":"","ruanke_rank":"9999","ruanke_level":"","is_video":2,"special_name":"\u9053\u8def\u6865\u6881\u4e0e\u6e21\u6cb3\u5de5\u7a0b","special_type":"1","type_name":"\u672c\u79d1","level3_name":"\u571f\u6728\u7c7b","level3_code":"72","level2_name":"\u5de5\u5b66","level2_id":"10","level2_code":"08","code":"0810"},{"id":"20592","school_id":"394","special_id":"1171","nation_feature":"2","province_feature":"2","is_important":"2","limit_year":"\u56db\u5e74","year":"2022","level3_weight":"0","nation_first_class":"2","xueke_rank":"0","xueke_rank_score":"","ruanke_rank":"9999","ruanke_level":"","is_video":2,"special_name":"\u57ce\u5e02\u5730\u4e0b\u7a7a\u95f4\u5de5\u7a0b","special_type":"1","type_name":"\u672c\u79d1","level3_name":"\u571f\u6728\u7c7b","level3_code":"72","level2_name":"\u5de5\u5b66","level2_id":"10","level2_code":"08","code":"0810"},{"id":"1035559","school_id":"394","special_id":"178","nation_feature":"2","province_feature":"2","is_important":"2","limit_year":"\u56db\u5e74","year":"2022","level3_weight":"0","nation_first_class":"2","xueke_rank":"0","xueke_rank_score":"","ruanke_rank":"215","ruanke_level":"B","is_video":2,"special_name":"\u571f\u6728\u5de5\u7a0b(\u4e2d\u5916\u5408\u4f5c\u529e\u5b66)","special_type":"1","type_name":"\u672c\u79d1","level3_name":"\u571f\u6728\u7c7b","level3_code":"72","level2_name":"\u5de5\u5b66","level2_id":"10","level2_code":"08","code":"0810"},{"id":"1130027","school_id":"394","special_id":"8393","nation_feature":"2","province_feature":"2","is_important":"2","limit_year":"\u56db\u5e74","year":"2022","level3_weight":"0","nation_first_class":"2","xueke_rank":"0","xueke_rank_score":"","ruanke_rank":"9999","ruanke_level":"","is_video":2,"special_name":"\u667a\u80fd\u5efa\u9020","special_type":"1","type_name":"\u672c\u79d1","level3_name":"\u571f\u6728\u7c7b","level3_code":"72","level2_name":"\u5de5\u5b66","level2_id":"10","level2_code":"08","code":"0810"}]},{"level3_weight":"0","code":"0811","name":"\u6c34\u5229\u7c7b(\u672c)","special":[{"id":"20606","school_id":"394","special_id":"183","nation_feature":"2","province_feature":"2","is_important":"2","limit_year":"\u56db\u5e74","year":"2022","level3_weight":"0","nation_first_class":"2","xueke_rank":"0","xueke_rank_score":"","ruanke_rank":"9999","ruanke_level":"","is_video":2,"special_name":"\u6c34\u6587\u4e0e\u6c34\u8d44\u6e90\u5de5\u7a0b","special_type":"1","type_name":"\u672c\u79d1","level3_name":"\u6c34\u5229\u7c7b","level3_code":"73","level2_name":"\u5de5\u5b66","level2_id":"10","level2_code":"08","code":"0811"},{"id":"20568","school_id":"394","special_id":"182","nation_feature":"2","province_feature":"1","is_important":"2","limit_year":"\u56db\u5e74","year":"2022","level3_weight":"0","nation_first_class":"2","xueke_rank":"0","xueke_rank_score":"","ruanke_rank":"9999","ruanke_level":"","is_video":2,"special_name":"\u6c34\u5229\u6c34\u7535\u5de5\u7a0b","special_type":"1","type_name":"\u672c\u79d1","level3_name":"\u6c34\u5229\u7c7b","level3_code":"73","level2_name":"\u5de5\u5b66","level2_id":"10","level2_code":"08","code":"0811"}]},{"level3_weight":"0","code":"0812","name":"\u6d4b\u7ed8\u7c7b(\u672c)","special":[{"id":"20570","school_id":"394","special_id":"185","nation_feature":"2","province_feature":"1","is_important":"2","limit_year":"\u56db\u5e74","year":"2022","level3_weight":"0","nation_first_class":"2","xueke_rank":"0","xueke_rank_score":"","ruanke_rank":"77","ruanke_level":"B","is_video":1,"special_name":"\u6d4b\u7ed8\u5de5\u7a0b","special_type":"1","type_name":"\u672c\u79d1","level3_name":"\u6d4b\u7ed8\u7c7b","level3_code":"74","level2_name":"\u5de5\u5b66","level2_id":"10","level2_code":"08","code":"0812"}]},{"level3_weight":"0","code":"0814","name":"\u5730\u8d28\u7c7b(\u672c)","special":[{"id":"20551","school_id":"394","special_id":"189","nation_feature":"2","province_feature":"2","is_important":"2","limit_year":"\u56db\u5e74","year":"2022","level3_weight":"0","nation_first_class":"2","xueke_rank":"0","xueke_rank_score":"","ruanke_rank":"9999","ruanke_level":"","is_video":2,"special_name":"\u5730\u8d28\u5de5\u7a0b","special_type":"1","type_name":"\u672c\u79d1","level3_name":"\u5730\u8d28\u7c7b","level3_code":"76","level2_name":"\u5de5\u5b66","level2_id":"10","level2_code":"08","code":"0814"},{"id":"20597","school_id":"394","special_id":"191","nation_feature":"2","province_feature":"1","is_important":"2","limit_year":"\u56db\u5e74","year":"2022","level3_weight":"0","nation_first_class":"2","xueke_rank":"0","xueke_rank_score":"","ruanke_rank":"9999","ruanke_level":"","is_video":2,"special_name":"\u8d44\u6e90\u52d8\u67e5\u5de5\u7a0b","special_type":"1","type_name":"\u672c\u79d1","level3_name":"\u5730\u8d28\u7c7b","level3_code":"76","level2_name":"\u5de5\u5b66","level2_id":"10","level2_code":"08","code":"0814"}]},{"level3_weight":"0","code":"0818","name":"\u4ea4\u901a\u8fd0\u8f93\u7c7b(\u672c)","special":[{"id":"2012332","school_id":"394","special_id":"9338","nation_feature":"2","province_feature":"2","is_important":"2","limit_year":"\u56db\u5e74","year":"2022","level3_weight":"0","nation_first_class":"2","xueke_rank":"0","xueke_rank_score":"","ruanke_rank":"9999","ruanke_level":"","is_video":2,"special_name":"\u667a\u80fd\u8fd0\u8f93\u5de5\u7a0b","special_type":"1","type_name":"\u672c\u79d1","level3_name":"\u4ea4\u901a\u8fd0\u8f93\u7c7b","level3_code":"80","level2_name":"\u5de5\u5b66","level2_id":"10","level2_code":"08","code":"0818"}]},{"level3_weight":"0","code":"0823","name":"\u519c\u4e1a\u5de5\u7a0b\u7c7b(\u672c)","special":[{"id":"20567","school_id":"394","special_id":"227","nation_feature":"2","province_feature":"2","is_important":"2","limit_year":"\u56db\u5e74","year":"2022","level3_weight":"0","nation_first_class":"2","xueke_rank":"0","xueke_rank_score":"","ruanke_rank":"9999","ruanke_level":"","is_video":2,"special_name":"\u519c\u4e1a\u6c34\u5229\u5de5\u7a0b","special_type":"1","type_name":"\u672c\u79d1","level3_name":"\u519c\u4e1a\u5de5\u7a0b\u7c7b","level3_code":"85","level2_name":"\u5de5\u5b66","level2_id":"10","level2_code":"08","code":"0823"}]},{"level3_weight":"0","code":"0825","name":"\u73af\u5883\u79d1\u5b66\u4e0e\u5de5\u7a0b\u7c7b(\u672c)","special":[{"id":"20572","school_id":"394","special_id":"232","nation_feature":"2","province_feature":"2","is_important":"2","limit_year":"\u56db\u5e74","year":"2022","level3_weight":"0","nation_first_class":"2","xueke_rank":"0","xueke_rank_score":"","ruanke_rank":"9999","ruanke_level":"","is_video":1,"special_name":"\u73af\u5883\u5de5\u7a0b","special_type":"1","type_name":"\u672c\u79d1","level3_name":"\u73af\u5883\u79d1\u5b66\u4e0e\u5de5\u7a0b\u7c7b","level3_code":"87","level2_name":"\u5de5\u5b66","level2_id":"10","level2_code":"08","code":"0825"},{"id":"20607","school_id":"394","special_id":"233","nation_feature":"2","province_feature":"2","is_important":"2","limit_year":"\u56db\u5e74","year":"2022","level3_weight":"0","nation_first_class":"2","xueke_rank":"0","xueke_rank_score":"","ruanke_rank":"9999","ruanke_level":"","is_video":2,"special_name":"\u73af\u5883\u79d1\u5b66","special_type":"1","type_name":"\u672c\u79d1","level3_name":"\u73af\u5883\u79d1\u5b66\u4e0e\u5de5\u7a0b\u7c7b","level3_code":"87","level2_name":"\u5de5\u5b66","level2_id":"10","level2_code":"08","code":"0825"}]},{"level3_weight":"0","code":"0828","name":"\u5efa\u7b51\u7c7b(\u672c)","special":[{"id":"20564","school_id":"394","special_id":"241","nation_feature":"2","province_feature":"2","is_important":"2","limit_year":"\u4e94\u5e74","year":"2022","level3_weight":"0","nation_first_class":"2","xueke_rank":"0","xueke_rank_score":"","ruanke_rank":"9999","ruanke_level":"","is_video":1,"special_name":"\u5efa\u7b51\u5b66","special_type":"1","type_name":"\u672c\u79d1","level3_name":"\u5efa\u7b51\u7c7b","level3_code":"90","level2_name":"\u5de5\u5b66","level2_id":"10","level2_code":"08","code":"0828"},{"id":"20565","school_id":"394","special_id":"242","nation_feature":"2","province_feature":"2","is_important":"2","limit_year":"\u56db\u5e74","year":"2022","level3_weight":"0","nation_first_class":"2","xueke_rank":"0","xueke_rank_score":"","ruanke_rank":"9999","ruanke_level":"","is_video":2,"special_name":"\u57ce\u4e61\u89c4\u5212","special_type":"1","type_name":"\u672c\u79d1","level3_name":"\u5efa\u7b51\u7c7b","level3_code":"90","level2_name":"\u5de5\u5b66","level2_id":"10","level2_code":"08","code":"0828"}]},{"level3_weight":"0","code":"0829","name":"\u5b89\u5168\u79d1\u5b66\u4e0e\u5de5\u7a0b\u7c7b(\u672c)","special":[{"id":"20608","school_id":"394","special_id":"244","nation_feature":"2","province_feature":"2","is_important":"2","limit_year":"\u56db\u5e74","year":"2022","level3_weight":"0","nation_first_class":"2","xueke_rank":"0","xueke_rank_score":"","ruanke_rank":"9999","ruanke_level":"","is_video":2,"special_name":"\u5b89\u5168\u5de5\u7a0b","special_type":"1","type_name":"\u672c\u79d1","level3_name":"\u5b89\u5168\u79d1\u5b66\u4e0e\u5de5\u7a0b\u7c7b","level3_code":"91","level2_name":"\u5de5\u5b66","level2_id":"10","level2_code":"08","code":"0829"},{"id":"1582484","school_id":"394","special_id":"8410","nation_feature":"2","province_feature":"2","is_important":"2","limit_year":"\u56db\u5e74","year":"2022","level3_weight":"0","nation_first_class":"2","xueke_rank":"0","xueke_rank_score":"","ruanke_rank":"9999","ruanke_level":"","is_video":1,"special_name":"\u5e94\u6025\u6280\u672f\u4e0e\u7ba1\u7406","special_type":"1","type_name":"\u672c\u79d1","level3_name":"\u5b89\u5168\u79d1\u5b66\u4e0e\u5de5\u7a0b\u7c7b","level3_code":"91","level2_name":"\u5de5\u5b66","level2_id":"10","level2_code":"08","code":"0829"}]},{"level3_weight":"0","code":"1201","name":"\u7ba1\u7406\u79d1\u5b66\u4e0e\u5de5\u7a0b\u7c7b(\u672c)","special":[{"id":"20575","school_id":"394","special_id":"296","nation_feature":"2","province_feature":"1","is_important":"2","limit_year":"\u56db\u5e74","year":"2022","level3_weight":"0","nation_first_class":"2","xueke_rank":"0","xueke_rank_score":"","ruanke_rank":"62","ruanke_level":"B","is_video":2,"special_name":"\u5de5\u7a0b\u9020\u4ef7","special_type":"1","type_name":"\u672c\u79d1","level3_name":"\u7ba1\u7406\u79d1\u5b66\u4e0e\u5de5\u7a0b\u7c7b","level3_code":"112","level2_name":"\u7ba1\u7406\u5b66","level2_id":"13","level2_code":"12","code":"1201"},{"id":"20574","school_id":"394","special_id":"294","nation_feature":"2","province_feature":"2","is_important":"2","limit_year":"\u56db\u5e74","year":"2022","level3_weight":"0","nation_first_class":"2","xueke_rank":"0","xueke_rank_score":"","ruanke_rank":"9999","ruanke_level":"","is_video":1,"special_name":"\u5de5\u7a0b\u7ba1\u7406","special_type":"1","type_name":"\u672c\u79d1","level3_name":"\u7ba1\u7406\u79d1\u5b66\u4e0e\u5de5\u7a0b\u7c7b","level3_code":"112","level2_name":"\u7ba1\u7406\u5b66","level2_id":"13","level2_code":"12","code":"1201"},{"id":"20577","school_id":"394","special_id":"295","nation_feature":"2","province_feature":"2","is_important":"2","limit_year":"\u56db\u5e74","year":"2022","level3_weight":"0","nation_first_class":"2","xueke_rank":"0","xueke_rank_score":"","ruanke_rank":"9999","ruanke_level":"","is_video":2,"special_name":"\u623f\u5730\u4ea7\u5f00\u53d1\u4e0e\u7ba1\u7406","special_type":"1","type_name":"\u672c\u79d1","level3_name":"\u7ba1\u7406\u79d1\u5b66\u4e0e\u5de5\u7a0b\u7c7b","level3_code":"112","level2_name":"\u7ba1\u7406\u5b66","level2_id":"13","level2_code":"12","code":"1201"},{"id":"2011901","school_id":"394","special_id":"8687","nation_feature":"2","province_feature":"2","is_important":"2","limit_year":"\u56db\u5e74","year":"2022","level3_weight":"0","nation_first_class":"2","xueke_rank":"0","xueke_rank_score":"","ruanke_rank":"9999","ruanke_level":"","is_video":2,"special_name":"\u5e94\u6025\u7ba1\u7406","special_type":"1","type_name":"\u672c\u79d1","level3_name":"\u7ba1\u7406\u79d1\u5b66\u4e0e\u5de5\u7a0b\u7c7b","level3_code":"112","level2_name":"\u7ba1\u7406\u5b66","level2_id":"13","level2_code":"12","code":"1201"}]},{"level3_weight":"0","code":"1202","name":"\u5de5\u5546\u7ba1\u7406\u7c7b(\u672c)","special":[{"id":"20603","school_id":"394","special_id":"300","nation_feature":"2","province_feature":"2","is_important":"2","limit_year":"\u56db\u5e74","year":"2022","level3_weight":"0","nation_first_class":"2","xueke_rank":"0","xueke_rank_score":"","ruanke_rank":"324","ruanke_level":"B","is_video":2,"special_name":"\u8d22\u52a1\u7ba1\u7406","special_type":"1","type_name":"\u672c\u79d1","level3_name":"\u5de5\u5546\u7ba1\u7406\u7c7b","level3_code":"113","level2_name":"\u7ba1\u7406\u5b66","level2_id":"13","level2_code":"12","code":"1202"},{"id":"20579","school_id":"394","special_id":"298","nation_feature":"2","province_feature":"2","is_important":"2","limit_year":"\u56db\u5e74","year":"2022","level3_weight":"0","nation_first_class":"2","xueke_rank":"0","xueke_rank_score":"","ruanke_rank":"9999","ruanke_level":"","is_video":2,"special_name":"\u5e02\u573a\u8425\u9500","special_type":"1","type_name":"\u672c\u79d1","level3_name":"\u5de5\u5546\u7ba1\u7406\u7c7b","level3_code":"113","level2_name":"\u7ba1\u7406\u5b66","level2_id":"13","level2_code":"12","code":"1202"},{"id":"20576","school_id":"394","special_id":"297","nation_feature":"2","province_feature":"2","is_important":"2","limit_year":"\u56db\u5e74","year":"2022","level3_weight":"0","nation_first_class":"2","xueke_rank":"0","xueke_rank_score":"","ruanke_rank":"9999","ruanke_level":"","is_video":2,"special_name":"\u5de5\u5546\u7ba1\u7406","special_type":"1","type_name":"\u672c\u79d1","level3_name":"\u5de5\u5546\u7ba1\u7406\u7c7b","level3_code":"113","level2_name":"\u7ba1\u7406\u5b66","level2_id":"13","level2_code":"12","code":"1202"}]},{"level3_weight":"0","code":"1305","name":"\u8bbe\u8ba1\u5b66\u7c7b(\u672c)","special":[{"id":"20582","school_id":"394","special_id":"349","nation_feature":"2","province_feature":"2","is_important":"2","limit_year":"\u56db\u5e74","year":"2022","level3_weight":"0","nation_first_class":"2","xueke_rank":"0","xueke_rank_score":"","ruanke_rank":"9999","ruanke_level":"","is_video":2,"special_name":"\u670d\u88c5\u4e0e\u670d\u9970\u8bbe\u8ba1","special_type":"1","type_name":"\u672c\u79d1","level3_name":"\u8bbe\u8ba1\u5b66\u7c7b","level3_code":"125","level2_name":"\u827a\u672f\u5b66","level2_id":"14","level2_code":"13","code":"1305"},{"id":"20583","school_id":"394","special_id":"348","nation_feature":"2","province_feature":"2","is_important":"2","limit_year":"\u56db\u5e74","year":"2022","level3_weight":"0","nation_first_class":"2","xueke_rank":"0","xueke_rank_score":"","ruanke_rank":"9999","ruanke_level":"","is_video":2,"special_name":"\u4ea7\u54c1\u8bbe\u8ba1","special_type":"1","type_name":"\u672c\u79d1","level3_name":"\u8bbe\u8ba1\u5b66\u7c7b","level3_code":"125","level2_name":"\u827a\u672f\u5b66","level2_id":"14","level2_code":"13","code":"1305"},{"id":"20584","school_id":"394","special_id":"347","nation_feature":"2","province_feature":"2","is_important":"2","limit_year":"\u56db\u5e74","year":"2022","level3_weight":"0","nation_first_class":"2","xueke_rank":"0","xueke_rank_score":"","ruanke_rank":"388","ruanke_level":"B","is_video":2,"special_name":"\u73af\u5883\u8bbe\u8ba1","special_type":"1","type_name":"\u672c\u79d1","level3_name":"\u8bbe\u8ba1\u5b66\u7c7b","level3_code":"125","level2_name":"\u827a\u672f\u5b66","level2_id":"14","level2_code":"13","code":"1305"},{"id":"20585","school_id":"394","special_id":"350","nation_feature":"2","province_feature":"2","is_important":"2","limit_year":"\u56db\u5e74","year":"2022","level3_weight":"0","nation_first_class":"2","xueke_rank":"0","xueke_rank_score":"","ruanke_rank":"9999","ruanke_level":"","is_video":2,"special_name":"\u516c\u5171\u827a\u672f","special_type":"1","type_name":"\u672c\u79d1","level3_name":"\u8bbe\u8ba1\u5b66\u7c7b","level3_code":"125","level2_name":"\u827a\u672f\u5b66","level2_id":"14","level2_code":"13","code":"1305"}]},{"level3_weight":"0","code":"4301","name":"\u7535\u529b\u6280\u672f\u7c7b(\u4e13)","special":[{"id":"20560","school_id":"394","special_id":"469","nation_feature":"2","province_feature":"2","is_important":"2","limit_year":"\u4e09\u5e74","year":"2022","level3_weight":"0","nation_first_class":"2","xueke_rank":"0","xueke_rank_score":"","ruanke_rank":"9999","ruanke_level":"","is_video":2,"special_name":"\u53d1\u7535\u5382\u53ca\u7535\u529b\u7cfb\u7edf","special_type":"2","type_name":"\u4e13\u79d1\uff08\u9ad8\u804c\uff09","level3_name":"\u7535\u529b\u6280\u672f\u7c7b","level3_code":"139","level2_name":"\u80fd\u6e90\u52a8\u529b\u4e0e\u6750\u6599\u5927\u7c7b","level2_id":"17","level2_code":"43","code":"4301"}]},{"level3_weight":"0","code":"4502","name":"\u6c34\u5229\u5de5\u7a0b\u4e0e\u7ba1\u7406\u7c7b(\u4e13)","special":[{"id":"20569","school_id":"394","special_id":"556","nation_feature":"2","province_feature":"2","is_important":"2","limit_year":"\u4e09\u5e74","year":"2022","level3_weight":"0","nation_first_class":"2","xueke_rank":"0","xueke_rank_score":"","ruanke_rank":"9999","ruanke_level":"","is_video":2,"special_name":"\u6c34\u5229\u6c34\u7535\u5efa\u7b51\u5de5\u7a0b","special_type":"2","type_name":"\u4e13\u79d1\uff08\u9ad8\u804c\uff09","level3_name":"\u6c34\u5229\u5de5\u7a0b\u4e0e\u7ba1\u7406\u7c7b","level3_code":"154","level2_name":"\u6c34\u5229\u5927\u7c7b","level2_id":"19","level2_code":"45","code":"4502"}]},{"level3_weight":"0","code":"4503","name":"\u6c34\u5229\u6c34\u7535\u8bbe\u5907\u7c7b(\u4e13)","special":[{"id":"1790246","school_id":"394","special_id":"8982","nation_feature":"2","province_feature":"2","is_important":"2","limit_year":"\u4e09\u5e74","year":"2022","level3_weight":"0","nation_first_class":"2","xueke_rank":"0","xueke_rank_score":"","ruanke_rank":"9999","ruanke_level":"","is_video":2,"special_name":"\u6c34\u7535\u7ad9\u8bbe\u5907\u5b89\u88c5\u4e0e\u7ba1\u7406","special_type":"2","type_name":"\u4e13\u79d1\uff08\u9ad8\u804c\uff09","level3_name":"\u6c34\u5229\u6c34\u7535\u8bbe\u5907\u7c7b","level3_code":"155","level2_name":"\u6c34\u5229\u5927\u7c7b","level2_id":"19","level2_code":"45","code":"4503"}]},{"level3_weight":"0","code":"4601","name":"\u673a\u68b0\u8bbe\u8ba1\u5236\u9020\u7c7b(\u4e13)","special":[{"id":"1790247","school_id":"394","special_id":"8990","nation_feature":"2","province_feature":"2","is_important":"2","limit_year":"\u4e09\u5e74","year":"2022","level3_weight":"0","nation_first_class":"2","xueke_rank":"0","xueke_rank_score":"","ruanke_rank":"9999","ruanke_level":"","is_video":2,"special_name":"\u667a\u80fd\u710a\u63a5\u6280\u672f","special_type":"2","type_name":"\u4e13\u79d1\uff08\u9ad8\u804c\uff09","level3_name":"\u673a\u68b0\u8bbe\u8ba1\u5236\u9020\u7c7b","level3_code":"157","level2_name":"\u88c5\u5907\u5236\u9020\u5927\u7c7b","level2_id":"20","level2_code":"46","code":"4601"},{"id":"1790248","school_id":"394","special_id":"9161","nation_feature":"2","province_feature":"2","is_important":"2","limit_year":"\u4e09\u5e74","year":"2022","level3_weight":"0","nation_first_class":"2","xueke_rank":"0","xueke_rank_score":"","ruanke_rank":"9999","ruanke_level":"","is_video":2,"special_name":"\u673a\u68b0\u5236\u9020\u53ca\u81ea\u52a8\u5316","special_type":"2","type_name":"\u4e13\u79d1\uff08\u9ad8\u804c\uff09","level3_name":"\u673a\u68b0\u8bbe\u8ba1\u5236\u9020\u7c7b","level3_code":"157","level2_name":"\u88c5\u5907\u5236\u9020\u5927\u7c7b","level2_id":"20","level2_code":"46","code":"4601"}]},{"level3_weight":"0","code":"5102","name":"\u8ba1\u7b97\u673a\u7c7b(\u4e13)","special":[{"id":"20609","school_id":"394","special_id":"784","nation_feature":"2","province_feature":"2","is_important":"2","limit_year":"\u4e09\u5e74","year":"2022","level3_weight":"0","nation_first_class":"2","xueke_rank":"0","xueke_rank_score":"","ruanke_rank":"9999","ruanke_level":"","is_video":2,"special_name":"\u8ba1\u7b97\u673a\u7f51\u7edc\u6280\u672f","special_type":"2","type_name":"\u4e13\u79d1\uff08\u9ad8\u804c\uff09","level3_name":"\u8ba1\u7b97\u673a\u7c7b","level3_code":"183","level2_name":"\u7535\u5b50\u4e0e\u4fe1\u606f\u5927\u7c7b","level2_id":"25","level2_code":"51","code":"5102"},{"id":"1790249","school_id":"394","special_id":"9176","nation_feature":"2","province_feature":"2","is_important":"2","limit_year":"\u4e09\u5e74","year":"2022","level3_weight":"0","nation_first_class":"2","xueke_rank":"0","xueke_rank_score":"","ruanke_rank":"9999","ruanke_level":"","is_video":2,"special_name":"\u6570\u5b57\u5a92\u4f53\u6280\u672f","special_type":"2","type_name":"\u4e13\u79d1\uff08\u9ad8\u804c\uff09","level3_name":"\u8ba1\u7b97\u673a\u7c7b","level3_code":"183","level2_name":"\u7535\u5b50\u4e0e\u4fe1\u606f\u5927\u7c7b","level2_id":"25","level2_code":"51","code":"5102"}]},{"level3_weight":"0","code":"5307","name":"\u7535\u5b50\u5546\u52a1\u7c7b(\u4e13)","special":[{"id":"20611","school_id":"394","special_id":"886","nation_feature":"2","province_feature":"2","is_important":"2","limit_year":"\u4e09\u5e74","year":"2022","level3_weight":"0","nation_first_class":"2","xueke_rank":"0","xueke_rank_score":"","ruanke_rank":"9999","ruanke_level":"","is_video":2,"special_name":"\u7535\u5b50\u5546\u52a1","special_type":"2","type_name":"\u4e13\u79d1\uff08\u9ad8\u804c\uff09","level3_name":"\u7535\u5b50\u5546\u52a1\u7c7b","level3_code":"200","level2_name":"\u8d22\u7ecf\u5546\u8d38\u5927\u7c7b","level2_id":"27","level2_code":"53","code":"5307"}]}],"nation_feature":[{"id":"20557","school_id":"394","special_id":"164","nation_feature":"1","province_feature":"1","is_important":"2","limit_year":"\u56db\u5e74","year":"2022","level3_weight":"0","nation_first_class":"2","xueke_rank":"0","xueke_rank_score":"","ruanke_rank":"179","ruanke_level":"B","is_video":1,"special_name":"\u7535\u6c14\u5de5\u7a0b\u53ca\u5176\u81ea\u52a8\u5316","special_type":"1","type_name":"\u672c\u79d1","level3_name":"\u7535\u6c14\u7c7b","level3_id":"68","level3_code":"68","level2_name":"\u5de5\u5b66","level2_id":"10","level2_code":"08","code":"0806"},{"id":"20552","school_id":"394","special_id":"147","nation_feature":"1","province_feature":"1","is_important":"2","limit_year":"\u56db\u5e74","year":"2022","level3_weight":"0","nation_first_class":"2","xueke_rank":"0","xueke_rank_score":"","ruanke_rank":"245","ruanke_level":"B","is_video":2,"special_name":"\u673a\u68b0\u8bbe\u8ba1\u5236\u9020\u53ca\u5176\u81ea\u52a8\u5316","special_type":"1","type_name":"\u672c\u79d1","level3_name":"\u673a\u68b0\u7c7b","level3_id":"64","level3_code":"64","level2_name":"\u5de5\u5b66","level2_id":"10","level2_code":"08","code":"0802"},{"id":"1035557","school_id":"394","special_id":"147","nation_feature":"1","province_feature":"2","is_important":"2","limit_year":"\u56db\u5e74","year":"2022","level3_weight":"0","nation_first_class":"2","xueke_rank":"0","xueke_rank_score":"","ruanke_rank":"245","ruanke_level":"B","is_video":2,"special_name":"\u673a\u68b0\u8bbe\u8ba1\u5236\u9020\u53ca\u5176\u81ea\u52a8\u5316(\u4e2d\u5916\u5408\u4f5c\u529e\u5b66)","special_type":"1","type_name":"\u672c\u79d1","level3_name":"\u673a\u68b0\u7c7b","level3_id":"64","level3_code":"64","level2_name":"\u5de5\u5b66","level2_id":"10","level2_code":"08","code":"0802"}],"educational_strength":{"num_doctor":"0","num_doctor2":"0","num_master":"0","num_master2":"0","num_subject":"0","gbh_num":"0","a_subject":"0","dualclass":0,"nation_feature":3}},"md5":"597f5c45227a303b3cfff762511728fe","time":"2024-06-26 03:08:24"}